{
  "code": 1,
  "msg": "Detail",
  "time": "1750214289",
  "data": {
    "id": 4766,
    "category_ids": "58,60",
    "title": "The King Of Nine-Five",
    "subtitle": "The King Of Nine-Five",
    "image": "https://liketv.oss-accelerate.aliyuncs.com/uploads/20250212/7717bed455a04f2eeee9c0a7e6e7cc8b.png",
    "description": "The King Of Nine-Five",
    "tags": "",
    "price": 15,
    "vprice": 5,
    "episodes": 79,
    "score": "90",
    "views": "763.07K",
    "favorites": "721.63K",
    "shares": "690.04K",
    "likes": "735.32K",
    "hots": "2910.07K",
    "is_favorite": 0,
    "episode_id": 0,
    "view_time": 0,
    "performer_list": [],
    "episodes_list": [
      {
        "track": "https://www.quicktv.vip/uploads/20240630/efa39b0be8a6df689f091f220563f596.vtt",
        "id": 348825,
        "vid": 4766,
        "name": "1",
        "image": "http://liketv.oss-accelerate.aliyuncs.com/videoimagelist/v4766/2024063017/b01feee4262517de253becb05e36f693.jpg",
        "duration": 90,
        "price": 0,
        "vprice": 0,
        "views": "9.78K",
        "favorites": "8.54K",
        "shares": "7.94K",
        "likes": "9.2K",
        "is_like": 0,
        "url": "https://liketv.oss-cn-hongkong.aliyuncs.com/0xiangxiang/%E4%B9%9D%E4%BA%94/1.mp4"
      },
      {
        "track": "https://www.quicktv.vip/uploads/20240630/194329c861029d461bbbe4510a20f883.vtt",
        "id": 348826,
        "vid": 4766,
        "name": "2",
        "image": "http://liketv.oss-accelerate.aliyuncs.com/videoimagelist/v4766/2024063017/b01feee4262517de253becb05e36f693.jpg",
        "duration": 88,
        "price": 0,
        "vprice": 0,
        "views": "9.1K",
        "favorites": "8.55K",
        "shares": "9.46K",
        "likes": "8.6K",
        "is_like": 0,
        "url": "https://liketv.oss-cn-hongkong.aliyuncs.com/0xiangxiang/%E4%B9%9D%E4%BA%94/2.mp4"
      },
      {
        "track": "https://www.quicktv.vip/uploads/20240630/d2878f69e9093b796024ec4f0a623974.vtt",
        "id": 348827,
        "vid": 4766,
        "name": "3",
        "image": "http://liketv.oss-accelerate.aliyuncs.com/videoimagelist/v4766/2024063017/b01feee4262517de253becb05e36f693.jpg",
        "duration": 92,
        "price": 0,
        "vprice": 0,
        "views": "9.27K",
        "favorites": "9.45K",
        "shares": "9.54K",
        "likes": "9.43K",
        "is_like": 0,
        "url": "https://liketv.oss-cn-hongkong.aliyuncs.com/0xiangxiang/%E4%B9%9D%E4%BA%94/3.mp4"
      },
      {
        "track": "https://www.quicktv.vip/uploads/20240630/fd292c7e1b41f2f563389cb215533bd6.vtt",
        "id": 348828,
        "vid": 4766,
        "name": "4",
        "image": "http://liketv.oss-accelerate.aliyuncs.com/videoimagelist/v4766/2024063017/b01feee4262517de253becb05e36f693.jpg",
        "duration": 97,
        "price": 0,
        "vprice": 0,
        "views": "8.78K",
        "favorites": "9.55K",
        "shares": "9.6K",
        "likes": "8.55K",
        "is_like": 0,
        "url": "https://liketv.oss-cn-hongkong.aliyuncs.com/0xiangxiang/%E4%B9%9D%E4%BA%94/4.mp4"
      },
      {
        "track": "https://www.quicktv.vip/uploads/20240630/27a8ec3c15f29ddf83255123043c407b.vtt",
        "id": 348829,
        "vid": 4766,
        "name": "5",
        "image": "http://liketv.oss-accelerate.aliyuncs.com/videoimagelist/v4766/2024063017/b01feee4262517de253becb05e36f693.jpg",
        "duration": 91,
        "price": 0,
        "vprice": 0,
        "views": "10.43K",
        "favorites": "8.29K",
        "shares": "8.08K",
        "likes": "9.89K",
        "is_like": 0,
        "url": "https://liketv.oss-cn-hongkong.aliyuncs.com/0xiangxiang/%E4%B9%9D%E4%BA%94/5.mp4"
      },
      {
        "track": "https://www.quicktv.vip/uploads/20240630/328d00102b982a348b1b95e24f50adee.vtt",
        "id": 348830,
        "vid": 4766,
        "name": "6",
        "image": "http://liketv.oss-accelerate.aliyuncs.com/videoimagelist/v4766/2024063017/b01feee4262517de253becb05e36f693.jpg",
        "duration": 97,
        "price": 0,
        "vprice": 0,
        "views": "9.87K",
        "favorites": "8.58K",
        "shares": "8.17K",
        "likes": "9.96K",
        "is_like": 0,
        "url": "https://liketv.oss-cn-hongkong.aliyuncs.com/0xiangxiang/%E4%B9%9D%E4%BA%94/6.mp4"
      },
      {
        "track": "https://www.quicktv.vip/uploads/20240630/6f36beda45324d0d61ed27b7a02bf210.vtt",
        "id": 348831,
        "vid": 4766,
        "name": "7",
        "image": "http://liketv.oss-accelerate.aliyuncs.com/videoimagelist/v4766/2024063017/b01feee4262517de253becb05e36f693.jpg",
        "duration": 90,
        "price": 0,
        "vprice": 0,
        "views": "9.15K",
        "favorites": "8.71K",
        "shares": "9.39K",
        "likes": "9.31K",
        "is_like": 0,
        "url": "https://liketv.oss-cn-hongkong.aliyuncs.com/0xiangxiang/%E4%B9%9D%E4%BA%94/7.mp4"
      },
      {
        "track": "https://www.quicktv.vip/uploads/20240630/d74eb6bc3b0fd5d05b47a08ac2f17215.vtt",
        "id": 348832,
        "vid": 4766,
        "name": "8",
        "image": "http://liketv.oss-accelerate.aliyuncs.com/videoimagelist/v4766/2024063017/b01feee4262517de253becb05e36f693.jpg",
        "duration": 93,
        "price": 0,
        "vprice": 0,
        "views": "9.04K",
        "favorites": "8.94K",
        "shares": "9.06K",
        "likes": "9.25K",
        "is_like": 0,
        "url": "https://liketv.oss-cn-hongkong.aliyuncs.com/0xiangxiang/%E4%B9%9D%E4%BA%94/8.mp4"
      },
      {
        "track": "https://www.quicktv.vip/uploads/20240630/232e01493f70cf0d2e92abf4408e1a3b.vtt",
        "id": 348833,
        "vid": 4766,
        "name": "9",
        "image": "http://liketv.oss-accelerate.aliyuncs.com/videoimagelist/v4766/2024063017/b01feee4262517de253becb05e36f693.jpg",
        "duration": 89,
        "price": 0,
        "vprice": 0,
        "views": "9.97K",
        "favorites": "10.03K",
        "shares": "8.48K",
        "likes": "8.84K",
        "is_like": 0,
        "url": "https://liketv.oss-cn-hongkong.aliyuncs.com/0xiangxiang/%E4%B9%9D%E4%BA%94/9.mp4"
      },
      {
        "track": "https://www.quicktv.vip/uploads/20240630/68e50ec47d2ea11e3501aaad208e945a.vtt",
        "id": 348834,
        "vid": 4766,
        "name": "10",
        "image": "http://liketv.oss-accelerate.aliyuncs.com/videoimagelist/v4766/2024063017/b01feee4262517de253becb05e36f693.jpg",
        "duration": 89,
        "price": 0,
        "vprice": 0,
        "views": "9.49K",
        "favorites": "9.23K",
        "shares": "8.73K",
        "likes": "9.68K",
        "is_like": 0,
        "url": "https://liketv.oss-cn-hongkong.aliyuncs.com/0xiangxiang/%E4%B9%9D%E4%BA%94/10.mp4"
      },
      {
        "track": "https://www.quicktv.vip/uploads/20240630/e6100f575e625eefe2e4c0fabc061b05.vtt",
        "id": 348835,
        "vid": 4766,
        "name": "11",
        "image": "http://liketv.oss-accelerate.aliyuncs.com/videoimagelist/v4766/2024063017/b01feee4262517de253becb05e36f693.jpg",
        "duration": 98,
        "price": 0,
        "vprice": 0,
        "views": "9.01K",
        "favorites": "9.49K",
        "shares": "8.63K",
        "likes": "9.47K",
        "is_like": 0,
        "url": "https://liketv.oss-cn-hongkong.aliyuncs.com/0xiangxiang/%E4%B9%9D%E4%BA%94/11.mp4"
      },
      {
        "track": "https://www.quicktv.vip/uploads/20240630/ff3706020edeb34e4b9b8355ba18661f.vtt",
        "id": 348836,
        "vid": 4766,
        "name": "12",
        "image": "http://liketv.oss-accelerate.aliyuncs.com/videoimagelist/v4766/2024063017/b01feee4262517de253becb05e36f693.jpg",
        "duration": 95,
        "price": 0,
        "vprice": 0,
        "views": "9.55K",
        "favorites": "9.97K",
        "shares": "9.6K",
        "likes": "9.54K",
        "is_like": 0,
        "url": "https://liketv.oss-cn-hongkong.aliyuncs.com/0xiangxiang/%E4%B9%9D%E4%BA%94/12.mp4"
      },
      {
        "track": "https://www.quicktv.vip/uploads/20240630/f8f180f971ba3e590f4b12a2ffb81043.vtt",
        "id": 348837,
        "vid": 4766,
        "name": "13",
        "image": "http://liketv.oss-accelerate.aliyuncs.com/videoimagelist/v4766/2024063017/b01feee4262517de253becb05e36f693.jpg",
        "duration": 94,
        "price": 0,
        "vprice": 0,
        "views": "9.35K",
        "favorites": "10K",
        "shares": "7.87K",
        "likes": "8.67K",
        "is_like": 0,
        "url": "https://liketv.oss-cn-hongkong.aliyuncs.com/0xiangxiang/%E4%B9%9D%E4%BA%94/13.mp4"
      },
      {
        "track": "https://www.quicktv.vip/uploads/20240630/467161e51dcff7e8e6c0518b71370b4e.vtt",
        "id": 348838,
        "vid": 4766,
        "name": "14",
        "image": "http://liketv.oss-accelerate.aliyuncs.com/videoimagelist/v4766/2024063017/b01feee4262517de253becb05e36f693.jpg",
        "duration": 93,
        "price": 0,
        "vprice": 0,
        "views": "8.68K",
        "favorites": "9.58K",
        "shares": "8.62K",
        "likes": "9.57K",
        "is_like": 0,
        "url": "https://liketv.oss-cn-hongkong.aliyuncs.com/0xiangxiang/%E4%B9%9D%E4%BA%94/14.mp4"
      },
      {
        "track": "https://www.quicktv.vip/uploads/20240630/434382e1acabc940ae2ee1e47ed6f2e2.vtt",
        "id": 348839,
        "vid": 4766,
        "name": "15",
        "image": "http://liketv.oss-accelerate.aliyuncs.com/videoimagelist/v4766/2024063017/b01feee4262517de253becb05e36f693.jpg",
        "duration": 88,
        "price": 0,
        "vprice": 0,
        "views": "9.89K",
        "favorites": "9.96K",
        "shares": "9K",
        "likes": "9.35K",
        "is_like": 0,
        "url": "https://liketv.oss-cn-hongkong.aliyuncs.com/0xiangxiang/%E4%B9%9D%E4%BA%94/15.mp4"
      },
      {
        "track": "https://www.quicktv.vip/uploads/20240630/933e833de4fea646a8e69edbb825f100.vtt",
        "id": 348840,
        "vid": 4766,
        "name": "16",
        "image": "http://liketv.oss-accelerate.aliyuncs.com/videoimagelist/v4766/2024063017/b01feee4262517de253becb05e36f693.jpg",
        "duration": 96,
        "price": 0,
        "vprice": 0,
        "views": "8.69K",
        "favorites": "8.79K",
        "shares": "9.47K",
        "likes": "8.58K",
        "is_like": 0,
        "url": "https://liketv.oss-cn-hongkong.aliyuncs.com/0xiangxiang/%E4%B9%9D%E4%BA%94/16.mp4"
      },
      {
        "track": "https://www.quicktv.vip/uploads/20240630/74d5ec6afaac4ac3c224b1e417ec1180.vtt",
        "id": 348841,
        "vid": 4766,
        "name": "17",
        "image": "http://liketv.oss-accelerate.aliyuncs.com/videoimagelist/v4766/2024063017/b01feee4262517de253becb05e36f693.jpg",
        "duration": 90,
        "price": 0,
        "vprice": 0,
        "views": "9.68K",
        "favorites": "9.83K",
        "shares": "8.59K",
        "likes": "8.52K",
        "is_like": 0,
        "url": "https://liketv.oss-cn-hongkong.aliyuncs.com/0xiangxiang/%E4%B9%9D%E4%BA%94/17.mp4"
      },
      {
        "track": "https://www.quicktv.vip/uploads/20240630/1e2bafd756319c1f2fc7e6526a87da77.vtt",
        "id": 348842,
        "vid": 4766,
        "name": "18",
        "image": "http://liketv.oss-accelerate.aliyuncs.com/videoimagelist/v4766/2024063017/b01feee4262517de253becb05e36f693.jpg",
        "duration": 92,
        "price": 0,
        "vprice": 0,
        "views": "9.52K",
        "favorites": "8.67K",
        "shares": "8.26K",
        "likes": "9.04K",
        "is_like": 0,
        "url": "https://liketv.oss-cn-hongkong.aliyuncs.com/0xiangxiang/%E4%B9%9D%E4%BA%94/18.mp4"
      },
      {
        "track": "https://www.quicktv.vip/uploads/20240630/aaf69d7aaa3df50de89d700f1cd91f77.vtt",
        "id": 348843,
        "vid": 4766,
        "name": "19",
        "image": "http://liketv.oss-accelerate.aliyuncs.com/videoimagelist/v4766/2024063017/b01feee4262517de253becb05e36f693.jpg",
        "duration": 96,
        "price": 0,
        "vprice": 0,
        "views": "9.71K",
        "favorites": "8.83K",
        "shares": "7.85K",
        "likes": "8.78K",
        "is_like": 0,
        "url": "https://liketv.oss-cn-hongkong.aliyuncs.com/0xiangxiang/%E4%B9%9D%E4%BA%94/19.mp4"
      },
      {
        "track": "https://www.quicktv.vip/uploads/20240630/a293dc95bd3669bac7ab262b4a077e63.vtt",
        "id": 348844,
        "vid": 4766,
        "name": "20",
        "image": "http://liketv.oss-accelerate.aliyuncs.com/videoimagelist/v4766/2024063017/b01feee4262517de253becb05e36f693.jpg",
        "duration": 98,
        "price": 0,
        "vprice": 0,
        "views": "9.74K",
        "favorites": "8.48K",
        "shares": "8.31K",
        "likes": "9.31K",
        "is_like": 0,
        "url": "https://liketv.oss-cn-hongkong.aliyuncs.com/0xiangxiang/%E4%B9%9D%E4%BA%94/20.mp4"
      },
      {
        "track": "https://www.quicktv.vip/uploads/20240630/d3dd45d7e4933d9bd5a92da7b1995c79.vtt",
        "id": 348845,
        "vid": 4766,
        "name": "21",
        "image": "http://liketv.oss-accelerate.aliyuncs.com/videoimagelist/v4766/2024063017/b01feee4262517de253becb05e36f693.jpg",
        "duration": 95,
        "price": 0,
        "vprice": 0,
        "views": "9.82K",
        "favorites": "8.95K",
        "shares": "8.66K",
        "likes": "9.99K",
        "is_like": 0,
        "url": "https://liketv.oss-cn-hongkong.aliyuncs.com/0xiangxiang/%E4%B9%9D%E4%BA%94/21.mp4"
      },
      {
        "track": "https://www.quicktv.vip/uploads/20240630/b8f62aa1489eb58dac49d5d0f1c26fb0.vtt",
        "id": 348846,
        "vid": 4766,
        "name": "22",
        "image": "http://liketv.oss-accelerate.aliyuncs.com/videoimagelist/v4766/2024063017/b01feee4262517de253becb05e36f693.jpg",
        "duration": 97,
        "price": 0,
        "vprice": 0,
        "views": "9.75K",
        "favorites": "8.65K",
        "shares": "9K",
        "likes": "8.68K",
        "is_like": 0,
        "url": "https://liketv.oss-cn-hongkong.aliyuncs.com/0xiangxiang/%E4%B9%9D%E4%BA%94/22.mp4"
      },
      {
        "track": "https://www.quicktv.vip/uploads/20240630/5d0791b44327d752674616cde2f07e9d.vtt",
        "id": 348847,
        "vid": 4766,
        "name": "23",
        "image": "http://liketv.oss-accelerate.aliyuncs.com/videoimagelist/v4766/2024063017/b01feee4262517de253becb05e36f693.jpg",
        "duration": 96,
        "price": 0,
        "vprice": 0,
        "views": "9.66K",
        "favorites": "9.71K",
        "shares": "9.45K",
        "likes": "9.33K",
        "is_like": 0,
        "url": "https://liketv.oss-cn-hongkong.aliyuncs.com/0xiangxiang/%E4%B9%9D%E4%BA%94/23.mp4"
      },
      {
        "track": "https://www.quicktv.vip/uploads/20240630/8f4363124fef9e2bba72e8e91634aebd.vtt",
        "id": 348848,
        "vid": 4766,
        "name": "24",
        "image": "http://liketv.oss-accelerate.aliyuncs.com/videoimagelist/v4766/2024063017/b01feee4262517de253becb05e36f693.jpg",
        "duration": 95,
        "price": 0,
        "vprice": 0,
        "views": "9.39K",
        "favorites": "9.27K",
        "shares": "7.9K",
        "likes": "9.38K",
        "is_like": 0,
        "url": "https://liketv.oss-cn-hongkong.aliyuncs.com/0xiangxiang/%E4%B9%9D%E4%BA%94/24.mp4"
      },
      {
        "track": "https://www.quicktv.vip/uploads/20240630/bfc25e45dc57619cc7d05151b5ae9f59.vtt",
        "id": 348849,
        "vid": 4766,
        "name": "25",
        "image": "http://liketv.oss-accelerate.aliyuncs.com/videoimagelist/v4766/2024063017/b01feee4262517de253becb05e36f693.jpg",
        "duration": 92,
        "price": 0,
        "vprice": 0,
        "views": "10.32K",
        "favorites": "8.93K",
        "shares": "9.18K",
        "likes": "9.17K",
        "is_like": 0,
        "url": "https://liketv.oss-cn-hongkong.aliyuncs.com/0xiangxiang/%E4%B9%9D%E4%BA%94/25.mp4"
      },
      {
        "track": "https://www.quicktv.vip/uploads/20240630/1c2a8072244edf588832a6eb7102f2fa.vtt",
        "id": 348850,
        "vid": 4766,
        "name": "26",
        "image": "http://liketv.oss-accelerate.aliyuncs.com/videoimagelist/v4766/2024063017/b01feee4262517de253becb05e36f693.jpg",
        "duration": 94,
        "price": 0,
        "vprice": 0,
        "views": "10.32K",
        "favorites": "8.53K",
        "shares": "7.88K",
        "likes": "8.88K",
        "is_like": 0,
        "url": "https://liketv.oss-cn-hongkong.aliyuncs.com/0xiangxiang/%E4%B9%9D%E4%BA%94/26.mp4"
      },
      {
        "track": "https://www.quicktv.vip/uploads/20240630/26b324d7aaaf10e4b820cf083ce5bfae.vtt",
        "id": 348851,
        "vid": 4766,
        "name": "27",
        "image": "http://liketv.oss-accelerate.aliyuncs.com/videoimagelist/v4766/2024063017/b01feee4262517de253becb05e36f693.jpg",
        "duration": 88,
        "price": 0,
        "vprice": 0,
        "views": "9.73K",
        "favorites": "9.34K",
        "shares": "8.37K",
        "likes": "9.95K",
        "is_like": 0,
        "url": "https://liketv.oss-cn-hongkong.aliyuncs.com/0xiangxiang/%E4%B9%9D%E4%BA%94/27.mp4"
      },
      {
        "track": "https://www.quicktv.vip/uploads/20240630/a7f6fc7319e7fa7e5c52fc553e489896.vtt",
        "id": 348852,
        "vid": 4766,
        "name": "28",
        "image": "http://liketv.oss-accelerate.aliyuncs.com/videoimagelist/v4766/2024063017/b01feee4262517de253becb05e36f693.jpg",
        "duration": 99,
        "price": 0,
        "vprice": 0,
        "views": "9.38K",
        "favorites": "9.47K",
        "shares": "9.64K",
        "likes": "8.72K",
        "is_like": 0,
        "url": "https://liketv.oss-cn-hongkong.aliyuncs.com/0xiangxiang/%E4%B9%9D%E4%BA%94/28.mp4"
      },
      {
        "track": "https://www.quicktv.vip/uploads/20240630/9780b290d4a58a924f609287fc5a21bf.vtt",
        "id": 348853,
        "vid": 4766,
        "name": "29",
        "image": "http://liketv.oss-accelerate.aliyuncs.com/videoimagelist/v4766/2024063017/b01feee4262517de253becb05e36f693.jpg",
        "duration": 99,
        "price": 0,
        "vprice": 0,
        "views": "9.81K",
        "favorites": "8.53K",
        "shares": "8.83K",
        "likes": "10.05K",
        "is_like": 0,
        "url": "https://liketv.oss-cn-hongkong.aliyuncs.com/0xiangxiang/%E4%B9%9D%E4%BA%94/29.mp4"
      },
      {
        "track": "https://www.quicktv.vip/uploads/20240630/1f73ae1e1a1804651c0e2ee017bb7e6a.vtt",
        "id": 348854,
        "vid": 4766,
        "name": "30",
        "image": "http://liketv.oss-accelerate.aliyuncs.com/videoimagelist/v4766/2024063017/b01feee4262517de253becb05e36f693.jpg",
        "duration": 92,
        "price": 0,
        "vprice": 0,
        "views": "10.37K",
        "favorites": "9.53K",
        "shares": "9.16K",
        "likes": "8.84K",
        "is_like": 0,
        "url": "https://liketv.oss-cn-hongkong.aliyuncs.com/0xiangxiang/%E4%B9%9D%E4%BA%94/30.mp4"
      },
      {
        "track": "https://www.quicktv.vip/uploads/20240630/8ce84637fa49475e327a2f791c7e0fea.vtt",
        "id": 348855,
        "vid": 4766,
        "name": "31",
        "image": "http://liketv.oss-accelerate.aliyuncs.com/videoimagelist/v4766/2024063017/b01feee4262517de253becb05e36f693.jpg",
        "duration": 90,
        "price": 0,
        "vprice": 0,
        "views": "9.42K",
        "favorites": "8.65K",
        "shares": "8.39K",
        "likes": "8.75K",
        "is_like": 0,
        "url": "https://liketv.oss-cn-hongkong.aliyuncs.com/0xiangxiang/%E4%B9%9D%E4%BA%94/31.mp4"
      },
      {
        "track": "https://www.quicktv.vip/uploads/20240630/78341a9024e7d1a96fb7ffe9ede65c06.vtt",
        "id": 348856,
        "vid": 4766,
        "name": "32",
        "image": "http://liketv.oss-accelerate.aliyuncs.com/videoimagelist/v4766/2024063017/b01feee4262517de253becb05e36f693.jpg",
        "duration": 99,
        "price": 0,
        "vprice": 0,
        "views": "8.9K",
        "favorites": "9.47K",
        "shares": "8.69K",
        "likes": "9.77K",
        "is_like": 0,
        "url": "https://liketv.oss-cn-hongkong.aliyuncs.com/0xiangxiang/%E4%B9%9D%E4%BA%94/32.mp4"
      },
      {
        "track": "https://www.quicktv.vip/uploads/20240630/146eaba65f88e23f1911bdc598992bb7.vtt",
        "id": 348857,
        "vid": 4766,
        "name": "33",
        "image": "http://liketv.oss-accelerate.aliyuncs.com/videoimagelist/v4766/2024063017/b01feee4262517de253becb05e36f693.jpg",
        "duration": 88,
        "price": 0,
        "vprice": 0,
        "views": "9.11K",
        "favorites": "9.79K",
        "shares": "9.42K",
        "likes": "9.11K",
        "is_like": 0,
        "url": "https://liketv.oss-cn-hongkong.aliyuncs.com/0xiangxiang/%E4%B9%9D%E4%BA%94/33.mp4"
      },
      {
        "track": "https://www.quicktv.vip/uploads/20240630/42880502f620cf3a6dea9265cf8a57af.vtt",
        "id": 348858,
        "vid": 4766,
        "name": "34",
        "image": "http://liketv.oss-accelerate.aliyuncs.com/videoimagelist/v4766/2024063017/b01feee4262517de253becb05e36f693.jpg",
        "duration": 90,
        "price": 0,
        "vprice": 0,
        "views": "10.15K",
        "favorites": "8.92K",
        "shares": "8.12K",
        "likes": "10.22K",
        "is_like": 0,
        "url": "https://liketv.oss-cn-hongkong.aliyuncs.com/0xiangxiang/%E4%B9%9D%E4%BA%94/34.mp4"
      },
      {
        "track": "https://www.quicktv.vip/uploads/20240630/e5168e30eed550df7f15e0741b232ae0.vtt",
        "id": 348859,
        "vid": 4766,
        "name": "35",
        "image": "http://liketv.oss-accelerate.aliyuncs.com/videoimagelist/v4766/2024063017/b01feee4262517de253becb05e36f693.jpg",
        "duration": 90,
        "price": 0,
        "vprice": 0,
        "views": "10.35K",
        "favorites": "9.08K",
        "shares": "8.51K",
        "likes": "8.7K",
        "is_like": 0,
        "url": "https://liketv.oss-cn-hongkong.aliyuncs.com/0xiangxiang/%E4%B9%9D%E4%BA%94/35.mp4"
      },
      {
        "track": "https://www.quicktv.vip/uploads/20240630/4bd35500a7511f89781ef074041b6d7a.vtt",
        "id": 348860,
        "vid": 4766,
        "name": "36",
        "image": "http://liketv.oss-accelerate.aliyuncs.com/videoimagelist/v4766/2024063017/b01feee4262517de253becb05e36f693.jpg",
        "duration": 95,
        "price": 0,
        "vprice": 0,
        "views": "9.53K",
        "favorites": "8.91K",
        "shares": "9.3K",
        "likes": "9.44K",
        "is_like": 0,
        "url": "https://liketv.oss-cn-hongkong.aliyuncs.com/0xiangxiang/%E4%B9%9D%E4%BA%94/36.mp4"
      },
      {
        "track": "https://www.quicktv.vip/uploads/20240630/69496c1a0d77edd7d815ca48181671f5.vtt",
        "id": 348861,
        "vid": 4766,
        "name": "37",
        "image": "http://liketv.oss-accelerate.aliyuncs.com/videoimagelist/v4766/2024063017/b01feee4262517de253becb05e36f693.jpg",
        "duration": 95,
        "price": 0,
        "vprice": 0,
        "views": "10.5K",
        "favorites": "9.64K",
        "shares": "9.24K",
        "likes": "9.32K",
        "is_like": 0,
        "url": "https://liketv.oss-cn-hongkong.aliyuncs.com/0xiangxiang/%E4%B9%9D%E4%BA%94/37.mp4"
      },
      {
        "track": "https://www.quicktv.vip/uploads/20240630/0e60258dee39b9ac71f1a66d186161f7.vtt",
        "id": 348862,
        "vid": 4766,
        "name": "38",
        "image": "http://liketv.oss-accelerate.aliyuncs.com/videoimagelist/v4766/2024063017/b01feee4262517de253becb05e36f693.jpg",
        "duration": 92,
        "price": 0,
        "vprice": 0,
        "views": "8.85K",
        "favorites": "9.03K",
        "shares": "8.26K",
        "likes": "8.53K",
        "is_like": 0,
        "url": "https://liketv.oss-cn-hongkong.aliyuncs.com/0xiangxiang/%E4%B9%9D%E4%BA%94/38.mp4"
      },
      {
        "track": "https://www.quicktv.vip/uploads/20240630/bdaf981cdb756bffe4658202d93b7d33.vtt",
        "id": 348863,
        "vid": 4766,
        "name": "39",
        "image": "http://liketv.oss-accelerate.aliyuncs.com/videoimagelist/v4766/2024063017/b01feee4262517de253becb05e36f693.jpg",
        "duration": 91,
        "price": 0,
        "vprice": 0,
        "views": "9.49K",
        "favorites": "8.68K",
        "shares": "9.63K",
        "likes": "9K",
        "is_like": 0,
        "url": "https://liketv.oss-cn-hongkong.aliyuncs.com/0xiangxiang/%E4%B9%9D%E4%BA%94/39.mp4"
      },
      {
        "track": "https://www.quicktv.vip/uploads/20240630/315bc9576186a9cff4561b7a21144854.vtt",
        "id": 348864,
        "vid": 4766,
        "name": "40",
        "image": "http://liketv.oss-accelerate.aliyuncs.com/videoimagelist/v4766/2024063017/b01feee4262517de253becb05e36f693.jpg",
        "duration": 93,
        "price": 0,
        "vprice": 0,
        "views": "9.17K",
        "favorites": "8.47K",
        "shares": "8.45K",
        "likes": "8.98K",
        "is_like": 0,
        "url": "https://liketv.oss-cn-hongkong.aliyuncs.com/0xiangxiang/%E4%B9%9D%E4%BA%94/40.mp4"
      },
      {
        "track": "https://www.quicktv.vip/uploads/20240630/f1ca21bc1f1ab158e0e3bf70d62b7fec.vtt",
        "id": 348865,
        "vid": 4766,
        "name": "41",
        "image": "http://liketv.oss-accelerate.aliyuncs.com/videoimagelist/v4766/2024063017/b01feee4262517de253becb05e36f693.jpg",
        "duration": 92,
        "price": 0,
        "vprice": 0,
        "views": "9.95K",
        "favorites": "9.21K",
        "shares": "8.43K",
        "likes": "10.25K",
        "is_like": 0,
        "url": "https://liketv.oss-cn-hongkong.aliyuncs.com/0xiangxiang/%E4%B9%9D%E4%BA%94/41.mp4"
      },
      {
        "track": "https://www.quicktv.vip/uploads/20240630/31299298f35ac5ad935718ebc2c4f41a.vtt",
        "id": 348866,
        "vid": 4766,
        "name": "42",
        "image": "http://liketv.oss-accelerate.aliyuncs.com/videoimagelist/v4766/2024063017/b01feee4262517de253becb05e36f693.jpg",
        "duration": 91,
        "price": 0,
        "vprice": 0,
        "views": "9.38K",
        "favorites": "8.48K",
        "shares": "8.09K",
        "likes": "9.95K",
        "is_like": 0,
        "url": "https://liketv.oss-cn-hongkong.aliyuncs.com/0xiangxiang/%E4%B9%9D%E4%BA%94/42.mp4"
      },
      {
        "track": "https://www.quicktv.vip/uploads/20240630/20dbba09af955bf3139fac96188fd796.vtt",
        "id": 348867,
        "vid": 4766,
        "name": "43",
        "image": "http://liketv.oss-accelerate.aliyuncs.com/videoimagelist/v4766/2024063017/b01feee4262517de253becb05e36f693.jpg",
        "duration": 88,
        "price": 0,
        "vprice": 0,
        "views": "10.35K",
        "favorites": "9.08K",
        "shares": "9.21K",
        "likes": "10.06K",
        "is_like": 0,
        "url": "https://liketv.oss-cn-hongkong.aliyuncs.com/0xiangxiang/%E4%B9%9D%E4%BA%94/43.mp4"
      },
      {
        "track": "https://www.quicktv.vip/uploads/20240630/90e36d8f9da3e0c94368c9b764c00b8e.vtt",
        "id": 348868,
        "vid": 4766,
        "name": "44",
        "image": "http://liketv.oss-accelerate.aliyuncs.com/videoimagelist/v4766/2024063017/b01feee4262517de253becb05e36f693.jpg",
        "duration": 91,
        "price": 0,
        "vprice": 0,
        "views": "9.2K",
        "favorites": "8.77K",
        "shares": "8.7K",
        "likes": "9.48K",
        "is_like": 0,
        "url": "https://liketv.oss-cn-hongkong.aliyuncs.com/0xiangxiang/%E4%B9%9D%E4%BA%94/44.mp4"
      },
      {
        "track": "https://www.quicktv.vip/uploads/20240630/b20731115f8e402b1e9efd6588f094c3.vtt",
        "id": 348869,
        "vid": 4766,
        "name": "45",
        "image": "http://liketv.oss-accelerate.aliyuncs.com/videoimagelist/v4766/2024063017/b01feee4262517de253becb05e36f693.jpg",
        "duration": 93,
        "price": 0,
        "vprice": 0,
        "views": "10.43K",
        "favorites": "9.8K",
        "shares": "8.75K",
        "likes": "9.55K",
        "is_like": 0,
        "url": "https://liketv.oss-cn-hongkong.aliyuncs.com/0xiangxiang/%E4%B9%9D%E4%BA%94/45.mp4"
      },
      {
        "track": "https://www.quicktv.vip/uploads/20240630/35528d4b58595c14fd0a5c8f2c336d75.vtt",
        "id": 348870,
        "vid": 4766,
        "name": "46",
        "image": "http://liketv.oss-accelerate.aliyuncs.com/videoimagelist/v4766/2024063017/b01feee4262517de253becb05e36f693.jpg",
        "duration": 96,
        "price": 0,
        "vprice": 0,
        "views": "8.76K",
        "favorites": "9.16K",
        "shares": "8.92K",
        "likes": "10.12K",
        "is_like": 0,
        "url": "https://liketv.oss-cn-hongkong.aliyuncs.com/0xiangxiang/%E4%B9%9D%E4%BA%94/46.mp4"
      },
      {
        "track": "https://www.quicktv.vip/uploads/20240630/77fa39a457185d0762464443bdf3f8ef.vtt",
        "id": 348871,
        "vid": 4766,
        "name": "47",
        "image": "http://liketv.oss-accelerate.aliyuncs.com/videoimagelist/v4766/2024063017/b01feee4262517de253becb05e36f693.jpg",
        "duration": 98,
        "price": 0,
        "vprice": 0,
        "views": "9.83K",
        "favorites": "9.44K",
        "shares": "8.36K",
        "likes": "9.5K",
        "is_like": 0,
        "url": "https://liketv.oss-cn-hongkong.aliyuncs.com/0xiangxiang/%E4%B9%9D%E4%BA%94/47.mp4"
      },
      {
        "track": "https://www.quicktv.vip/uploads/20240630/8064357eff77cdbccca7bce0a6e61abe.vtt",
        "id": 348872,
        "vid": 4766,
        "name": "48",
        "image": "http://liketv.oss-accelerate.aliyuncs.com/videoimagelist/v4766/2024063017/b01feee4262517de253becb05e36f693.jpg",
        "duration": 96,
        "price": 0,
        "vprice": 0,
        "views": "9.07K",
        "favorites": "9.47K",
        "shares": "8.44K",
        "likes": "8.76K",
        "is_like": 0,
        "url": "https://liketv.oss-cn-hongkong.aliyuncs.com/0xiangxiang/%E4%B9%9D%E4%BA%94/48.mp4"
      },
      {
        "track": "https://www.quicktv.vip/uploads/20240630/5a7bbc11e1c9d9e234184488a0cf26e2.vtt",
        "id": 348873,
        "vid": 4766,
        "name": "49",
        "image": "http://liketv.oss-accelerate.aliyuncs.com/videoimagelist/v4766/2024063017/b01feee4262517de253becb05e36f693.jpg",
        "duration": 93,
        "price": 0,
        "vprice": 0,
        "views": "8.86K",
        "favorites": "9.94K",
        "shares": "8.71K",
        "likes": "8.99K",
        "is_like": 0,
        "url": "https://liketv.oss-cn-hongkong.aliyuncs.com/0xiangxiang/%E4%B9%9D%E4%BA%94/49.mp4"
      },
      {
        "track": "https://www.quicktv.vip/uploads/20240630/15bb94192c88d3c0e4dfccb28b6f7375.vtt",
        "id": 348874,
        "vid": 4766,
        "name": "50",
        "image": "http://liketv.oss-accelerate.aliyuncs.com/videoimagelist/v4766/2024063017/b01feee4262517de253becb05e36f693.jpg",
        "duration": 93,
        "price": 0,
        "vprice": 0,
        "views": "9.71K",
        "favorites": "8.65K",
        "shares": "8.15K",
        "likes": "10.02K",
        "is_like": 0,
        "url": "https://liketv.oss-cn-hongkong.aliyuncs.com/0xiangxiang/%E4%B9%9D%E4%BA%94/50.mp4"
      },
      {
        "track": "https://www.quicktv.vip/uploads/20240630/2654da8ca0a0e49b7e04f51e968d5aca.vtt",
        "id": 348875,
        "vid": 4766,
        "name": "51",
        "image": "http://liketv.oss-accelerate.aliyuncs.com/videoimagelist/v4766/2024063017/b01feee4262517de253becb05e36f693.jpg",
        "duration": 99,
        "price": 0,
        "vprice": 0,
        "views": "10.15K",
        "favorites": "9.64K",
        "shares": "7.98K",
        "likes": "9.95K",
        "is_like": 0,
        "url": "https://liketv.oss-cn-hongkong.aliyuncs.com/0xiangxiang/%E4%B9%9D%E4%BA%94/51.mp4"
      },
      {
        "track": "https://www.quicktv.vip/uploads/20240630/f5da352bf729208ca355e2e6e19f41d1.vtt",
        "id": 348876,
        "vid": 4766,
        "name": "52",
        "image": "http://liketv.oss-accelerate.aliyuncs.com/videoimagelist/v4766/2024063017/b01feee4262517de253becb05e36f693.jpg",
        "duration": 95,
        "price": 0,
        "vprice": 0,
        "views": "8.91K",
        "favorites": "9.5K",
        "shares": "8.97K",
        "likes": "9.96K",
        "is_like": 0,
        "url": "https://liketv.oss-cn-hongkong.aliyuncs.com/0xiangxiang/%E4%B9%9D%E4%BA%94/52.mp4"
      },
      {
        "track": "https://www.quicktv.vip/uploads/20240630/9c76720df98a341d308b456b7df4acd9.vtt",
        "id": 348877,
        "vid": 4766,
        "name": "53",
        "image": "http://liketv.oss-accelerate.aliyuncs.com/videoimagelist/v4766/2024063017/b01feee4262517de253becb05e36f693.jpg",
        "duration": 98,
        "price": 0,
        "vprice": 0,
        "views": "9.82K",
        "favorites": "8.92K",
        "shares": "8.78K",
        "likes": "9.44K",
        "is_like": 0,
        "url": "https://liketv.oss-cn-hongkong.aliyuncs.com/0xiangxiang/%E4%B9%9D%E4%BA%94/53.mp4"
      },
      {
        "track": "https://www.quicktv.vip/uploads/20240630/764749c992cf607daf4204b32fb1405a.vtt",
        "id": 348878,
        "vid": 4766,
        "name": "54",
        "image": "http://liketv.oss-accelerate.aliyuncs.com/videoimagelist/v4766/2024063017/b01feee4262517de253becb05e36f693.jpg",
        "duration": 99,
        "price": 0,
        "vprice": 0,
        "views": "9.93K",
        "favorites": "9.86K",
        "shares": "8.51K",
        "likes": "8.83K",
        "is_like": 0,
        "url": "https://liketv.oss-cn-hongkong.aliyuncs.com/0xiangxiang/%E4%B9%9D%E4%BA%94/54.mp4"
      },
      {
        "track": "https://www.quicktv.vip/uploads/20240630/173d3965c4ae30ad55018020cbb923fd.vtt",
        "id": 348879,
        "vid": 4766,
        "name": "55",
        "image": "http://liketv.oss-accelerate.aliyuncs.com/videoimagelist/v4766/2024063017/b01feee4262517de253becb05e36f693.jpg",
        "duration": 98,
        "price": 0,
        "vprice": 0,
        "views": "9.12K",
        "favorites": "9.12K",
        "shares": "9.04K",
        "likes": "9.23K",
        "is_like": 0,
        "url": "https://liketv.oss-cn-hongkong.aliyuncs.com/0xiangxiang/%E4%B9%9D%E4%BA%94/55.mp4"
      },
      {
        "track": "https://www.quicktv.vip/uploads/20240630/96bd26fac0031922a661de5090a08deb.vtt",
        "id": 348880,
        "vid": 4766,
        "name": "56",
        "image": "http://liketv.oss-accelerate.aliyuncs.com/videoimagelist/v4766/2024063017/b01feee4262517de253becb05e36f693.jpg",
        "duration": 96,
        "price": 0,
        "vprice": 0,
        "views": "9.4K",
        "favorites": "8.75K",
        "shares": "8.79K",
        "likes": "9.9K",
        "is_like": 0,
        "url": "https://liketv.oss-cn-hongkong.aliyuncs.com/0xiangxiang/%E4%B9%9D%E4%BA%94/56.mp4"
      },
      {
        "track": "https://www.quicktv.vip/uploads/20240630/8fd9cf7578cd7813335aa26a3533f895.vtt",
        "id": 348881,
        "vid": 4766,
        "name": "57",
        "image": "http://liketv.oss-accelerate.aliyuncs.com/videoimagelist/v4766/2024063017/b01feee4262517de253becb05e36f693.jpg",
        "duration": 91,
        "price": 0,
        "vprice": 0,
        "views": "9.79K",
        "favorites": "9.99K",
        "shares": "8.38K",
        "likes": "10.14K",
        "is_like": 0,
        "url": "https://liketv.oss-cn-hongkong.aliyuncs.com/0xiangxiang/%E4%B9%9D%E4%BA%94/57.mp4"
      },
      {
        "track": "https://www.quicktv.vip/uploads/20240630/57024bb963b0963bc1f800f3f726adfe.vtt",
        "id": 348882,
        "vid": 4766,
        "name": "58",
        "image": "http://liketv.oss-accelerate.aliyuncs.com/videoimagelist/v4766/2024063017/b01feee4262517de253becb05e36f693.jpg",
        "duration": 88,
        "price": 0,
        "vprice": 0,
        "views": "10.08K",
        "favorites": "9.29K",
        "shares": "8.26K",
        "likes": "8.48K",
        "is_like": 0,
        "url": "https://liketv.oss-cn-hongkong.aliyuncs.com/0xiangxiang/%E4%B9%9D%E4%BA%94/58.mp4"
      },
      {
        "track": "https://www.quicktv.vip/uploads/20240630/65f81e0ef81c4990ce57db329274012e.vtt",
        "id": 348883,
        "vid": 4766,
        "name": "59",
        "image": "http://liketv.oss-accelerate.aliyuncs.com/videoimagelist/v4766/2024063017/b01feee4262517de253becb05e36f693.jpg",
        "duration": 92,
        "price": 0,
        "vprice": 0,
        "views": "9.35K",
        "favorites": "8.52K",
        "shares": "9.49K",
        "likes": "9.87K",
        "is_like": 0,
        "url": "https://liketv.oss-cn-hongkong.aliyuncs.com/0xiangxiang/%E4%B9%9D%E4%BA%94/59.mp4"
      },
      {
        "track": "https://www.quicktv.vip/uploads/20240630/805a0306c31eeb48163506b688661bca.vtt",
        "id": 348884,
        "vid": 4766,
        "name": "60",
        "image": "http://liketv.oss-accelerate.aliyuncs.com/videoimagelist/v4766/2024063017/b01feee4262517de253becb05e36f693.jpg",
        "duration": 89,
        "price": 0,
        "vprice": 0,
        "views": "10.42K",
        "favorites": "9.25K",
        "shares": "8.32K",
        "likes": "9.3K",
        "is_like": 0,
        "url": "https://liketv.oss-cn-hongkong.aliyuncs.com/0xiangxiang/%E4%B9%9D%E4%BA%94/60.mp4"
      },
      {
        "track": "https://www.quicktv.vip/uploads/20240630/15f4318ffee578db5137ef0c85896999.vtt",
        "id": 348885,
        "vid": 4766,
        "name": "61",
        "image": "http://liketv.oss-accelerate.aliyuncs.com/videoimagelist/v4766/2024063017/b01feee4262517de253becb05e36f693.jpg",
        "duration": 97,
        "price": 0,
        "vprice": 0,
        "views": "10.11K",
        "favorites": "9.68K",
        "shares": "8.9K",
        "likes": "8.87K",
        "is_like": 0,
        "url": "https://liketv.oss-cn-hongkong.aliyuncs.com/0xiangxiang/%E4%B9%9D%E4%BA%94/61.mp4"
      },
      {
        "track": "https://www.quicktv.vip/uploads/20240630/29fc1372479fe79fe40285488fd970b8.vtt",
        "id": 348886,
        "vid": 4766,
        "name": "62",
        "image": "http://liketv.oss-accelerate.aliyuncs.com/videoimagelist/v4766/2024063017/b01feee4262517de253becb05e36f693.jpg",
        "duration": 96,
        "price": 0,
        "vprice": 0,
        "views": "9.39K",
        "favorites": "9.16K",
        "shares": "9.05K",
        "likes": "8.56K",
        "is_like": 0,
        "url": "https://liketv.oss-cn-hongkong.aliyuncs.com/0xiangxiang/%E4%B9%9D%E4%BA%94/62.mp4"
      },
      {
        "track": "https://www.quicktv.vip/uploads/20240630/4a48945de47fee08907c83bb2ea7e7fc.vtt",
        "id": 348887,
        "vid": 4766,
        "name": "63",
        "image": "http://liketv.oss-accelerate.aliyuncs.com/videoimagelist/v4766/2024063017/b01feee4262517de253becb05e36f693.jpg",
        "duration": 88,
        "price": 0,
        "vprice": 0,
        "views": "9.13K",
        "favorites": "9.12K",
        "shares": "9.64K",
        "likes": "9.2K",
        "is_like": 0,
        "url": "https://liketv.oss-cn-hongkong.aliyuncs.com/0xiangxiang/%E4%B9%9D%E4%BA%94/63.mp4"
      },
      {
        "track": "https://www.quicktv.vip/uploads/20240630/167af4d71533a919cda181f47f8ab10a.vtt",
        "id": 348888,
        "vid": 4766,
        "name": "64",
        "image": "http://liketv.oss-accelerate.aliyuncs.com/videoimagelist/v4766/2024063017/b01feee4262517de253becb05e36f693.jpg",
        "duration": 97,
        "price": 0,
        "vprice": 0,
        "views": "10.15K",
        "favorites": "9.47K",
        "shares": "8.42K",
        "likes": "9.89K",
        "is_like": 0,
        "url": "https://liketv.oss-cn-hongkong.aliyuncs.com/0xiangxiang/%E4%B9%9D%E4%BA%94/64.mp4"
      },
      {
        "track": "https://www.quicktv.vip/uploads/20240630/4e24018ec5bc0bf2bc9cfa852d28c291.vtt",
        "id": 348889,
        "vid": 4766,
        "name": "65",
        "image": "http://liketv.oss-accelerate.aliyuncs.com/videoimagelist/v4766/2024063017/b01feee4262517de253becb05e36f693.jpg",
        "duration": 95,
        "price": 0,
        "vprice": 0,
        "views": "10.06K",
        "favorites": "9.62K",
        "shares": "8.84K",
        "likes": "8.95K",
        "is_like": 0,
        "url": "https://liketv.oss-cn-hongkong.aliyuncs.com/0xiangxiang/%E4%B9%9D%E4%BA%94/65.mp4"
      },
      {
        "track": "https://www.quicktv.vip/uploads/20240630/eb3e2cba16ca66c272052442b95400d6.vtt",
        "id": 348890,
        "vid": 4766,
        "name": "66",
        "image": "http://liketv.oss-accelerate.aliyuncs.com/videoimagelist/v4766/2024063017/b01feee4262517de253becb05e36f693.jpg",
        "duration": 90,
        "price": 0,
        "vprice": 0,
        "views": "9.45K",
        "favorites": "8.3K",
        "shares": "7.84K",
        "likes": "9.15K",
        "is_like": 0,
        "url": "https://liketv.oss-cn-hongkong.aliyuncs.com/0xiangxiang/%E4%B9%9D%E4%BA%94/66.mp4"
      },
      {
        "track": "https://www.quicktv.vip/uploads/20240630/dfb6c8bf8ac65061cd61e8577a93b009.vtt",
        "id": 348891,
        "vid": 4766,
        "name": "67",
        "image": "http://liketv.oss-accelerate.aliyuncs.com/videoimagelist/v4766/2024063017/b01feee4262517de253becb05e36f693.jpg",
        "duration": 93,
        "price": 0,
        "vprice": 0,
        "views": "9.66K",
        "favorites": "8.63K",
        "shares": "7.92K",
        "likes": "9.11K",
        "is_like": 0,
        "url": "https://liketv.oss-cn-hongkong.aliyuncs.com/0xiangxiang/%E4%B9%9D%E4%BA%94/67.mp4"
      },
      {
        "track": "https://www.quicktv.vip/uploads/20240630/d5c93c4dc6e9c409b353ec622d8cb35a.vtt",
        "id": 348892,
        "vid": 4766,
        "name": "68",
        "image": "http://liketv.oss-accelerate.aliyuncs.com/videoimagelist/v4766/2024063017/b01feee4262517de253becb05e36f693.jpg",
        "duration": 89,
        "price": 0,
        "vprice": 0,
        "views": "10.44K",
        "favorites": "8.46K",
        "shares": "9.29K",
        "likes": "8.59K",
        "is_like": 0,
        "url": "https://liketv.oss-cn-hongkong.aliyuncs.com/0xiangxiang/%E4%B9%9D%E4%BA%94/68.mp4"
      },
      {
        "track": "https://www.quicktv.vip/uploads/20240630/ce2a1335b47b50dbeacf1f03216fedf4.vtt",
        "id": 348893,
        "vid": 4766,
        "name": "69",
        "image": "http://liketv.oss-accelerate.aliyuncs.com/videoimagelist/v4766/2024063017/b01feee4262517de253becb05e36f693.jpg",
        "duration": 93,
        "price": 0,
        "vprice": 0,
        "views": "9.48K",
        "favorites": "9.85K",
        "shares": "8.79K",
        "likes": "9K",
        "is_like": 0,
        "url": "https://liketv.oss-cn-hongkong.aliyuncs.com/0xiangxiang/%E4%B9%9D%E4%BA%94/69.mp4"
      },
      {
        "track": "https://www.quicktv.vip/uploads/20240630/b3a969e0e86de06b638dab89beb93501.vtt",
        "id": 348894,
        "vid": 4766,
        "name": "70",
        "image": "http://liketv.oss-accelerate.aliyuncs.com/videoimagelist/v4766/2024063017/b01feee4262517de253becb05e36f693.jpg",
        "duration": 91,
        "price": 10,
        "vprice": 1,
        "views": "9.18K",
        "favorites": "8.41K",
        "shares": "8.1K",
        "likes": "9.48K",
        "is_like": 0,
        "url": "https://liketv.oss-cn-hongkong.aliyuncs.com/0xiangxiang/%E4%B9%9D%E4%BA%94/70.mp4"
      },
      {
        "track": "https://www.quicktv.vip/uploads/20240630/0422016643f4fca14249c04d92431624.vtt",
        "id": 348895,
        "vid": 4766,
        "name": "71",
        "image": "http://liketv.oss-accelerate.aliyuncs.com/videoimagelist/v4766/2024063017/b01feee4262517de253becb05e36f693.jpg",
        "duration": 98,
        "price": 10,
        "vprice": 1,
        "views": "10.35K",
        "favorites": "9.66K",
        "shares": "9.57K",
        "likes": "9.38K",
        "is_like": 0,
        "url": "https://liketv.oss-cn-hongkong.aliyuncs.com/0xiangxiang/%E4%B9%9D%E4%BA%94/71.mp4"
      },
      {
        "track": "https://www.quicktv.vip/uploads/20240630/a98ae468d6d7cc6abce328c89288d9fc.vtt",
        "id": 348896,
        "vid": 4766,
        "name": "72",
        "image": "http://liketv.oss-accelerate.aliyuncs.com/videoimagelist/v4766/2024063017/b01feee4262517de253becb05e36f693.jpg",
        "duration": 90,
        "price": 10,
        "vprice": 1,
        "views": "10K",
        "favorites": "8.81K",
        "shares": "9.65K",
        "likes": "9.13K",
        "is_like": 0,
        "url": "https://liketv.oss-cn-hongkong.aliyuncs.com/0xiangxiang/%E4%B9%9D%E4%BA%94/72.mp4"
      },
      {
        "track": "https://www.quicktv.vip/uploads/20240630/a13201be5c04aaa9dc4750fc28ca18b7.vtt",
        "id": 348897,
        "vid": 4766,
        "name": "73",
        "image": "http://liketv.oss-accelerate.aliyuncs.com/videoimagelist/v4766/2024063017/b01feee4262517de253becb05e36f693.jpg",
        "duration": 89,
        "price": 10,
        "vprice": 1,
        "views": "10.23K",
        "favorites": "8.32K",
        "shares": "8.37K",
        "likes": "10.09K",
        "is_like": 0,
        "url": "https://liketv.oss-cn-hongkong.aliyuncs.com/0xiangxiang/%E4%B9%9D%E4%BA%94/73.mp4"
      },
      {
        "track": "https://www.quicktv.vip/uploads/20240630/c5a706f782372342d068fbfb073bffb9.vtt",
        "id": 348898,
        "vid": 4766,
        "name": "74",
        "image": "http://liketv.oss-accelerate.aliyuncs.com/videoimagelist/v4766/2024063017/b01feee4262517de253becb05e36f693.jpg",
        "duration": 97,
        "price": 10,
        "vprice": 1,
        "views": "8.87K",
        "favorites": "8.51K",
        "shares": "8.02K",
        "likes": "9.61K",
        "is_like": 0,
        "url": "https://liketv.oss-cn-hongkong.aliyuncs.com/0xiangxiang/%E4%B9%9D%E4%BA%94/74.mp4"
      },
      {
        "track": "https://www.quicktv.vip/uploads/20240630/8e5355a8ca3f4b5dca5f9b2f9f62cc8f.vtt",
        "id": 348899,
        "vid": 4766,
        "name": "75",
        "image": "http://liketv.oss-accelerate.aliyuncs.com/videoimagelist/v4766/2024063017/b01feee4262517de253becb05e36f693.jpg",
        "duration": 99,
        "price": 10,
        "vprice": 1,
        "views": "10.46K",
        "favorites": "9.03K",
        "shares": "8.27K",
        "likes": "9.79K",
        "is_like": 0,
        "url": "https://liketv.oss-cn-hongkong.aliyuncs.com/0xiangxiang/%E4%B9%9D%E4%BA%94/75.mp4"
      },
      {
        "track": "https://www.quicktv.vip/uploads/20240630/a8af04c171473f812cf87a14d98cd32a.vtt",
        "id": 348900,
        "vid": 4766,
        "name": "76",
        "image": "http://liketv.oss-accelerate.aliyuncs.com/videoimagelist/v4766/2024063017/b01feee4262517de253becb05e36f693.jpg",
        "duration": 95,
        "price": 10,
        "vprice": 1,
        "views": "10.49K",
        "favorites": "9.55K",
        "shares": "8.76K",
        "likes": "8.87K",
        "is_like": 0,
        "url": "https://liketv.oss-cn-hongkong.aliyuncs.com/0xiangxiang/%E4%B9%9D%E4%BA%94/76.mp4"
      },
      {
        "track": "https://www.quicktv.vip/uploads/20240630/09cdf33da6f0fed7cd9c37ee033b4863.vtt",
        "id": 348901,
        "vid": 4766,
        "name": "77",
        "image": "http://liketv.oss-accelerate.aliyuncs.com/videoimagelist/v4766/2024063017/b01feee4262517de253becb05e36f693.jpg",
        "duration": 89,
        "price": 10,
        "vprice": 1,
        "views": "9.53K",
        "favorites": "8.91K",
        "shares": "9.33K",
        "likes": "9.32K",
        "is_like": 0,
        "url": "https://liketv.oss-cn-hongkong.aliyuncs.com/0xiangxiang/%E4%B9%9D%E4%BA%94/77.mp4"
      },
      {
        "track": "https://www.quicktv.vip/uploads/20240630/c70d84ec729d885d378337b535bf8977.vtt",
        "id": 348902,
        "vid": 4766,
        "name": "78",
        "image": "http://liketv.oss-accelerate.aliyuncs.com/videoimagelist/v4766/2024063017/b01feee4262517de253becb05e36f693.jpg",
        "duration": 95,
        "price": 10,
        "vprice": 1,
        "views": "10.19K",
        "favorites": "9.04K",
        "shares": "9.46K",
        "likes": "9.19K",
        "is_like": 0,
        "url": "https://liketv.oss-cn-hongkong.aliyuncs.com/0xiangxiang/%E4%B9%9D%E4%BA%94/78.mp4"
      },
      {
        "track": "https://www.quicktv.vip/uploads/20240630/52bb8101cf7e21cbc3b5033a75449027.vtt",
        "id": 348903,
        "vid": 4766,
        "name": "79",
        "image": "http://liketv.oss-accelerate.aliyuncs.com/videoimagelist/v4766/2024063017/b01feee4262517de253becb05e36f693.jpg",
        "duration": 89,
        "price": 10,
        "vprice": 1,
        "views": "10.33K",
        "favorites": "8.9K",
        "shares": "8.45K",
        "likes": "8.67K",
        "is_like": 0,
        "url": "https://liketv.oss-cn-hongkong.aliyuncs.com/0xiangxiang/%E4%B9%9D%E4%BA%94/79.mp4"
      }
    ],
    "adsurl": "https://liketv.oss-cn-hongkong.aliyuncs.com/00quicktv/3.mp4",
    "tags_arr": [],
    "category_text_arr": [],
    "year_text": "",
    "area_text": ""
  }
}