{
  "code": 1,
  "msg": "Detail",
  "time": "1750214419",
  "data": {
    "id": 10858,
    "category_ids": "57",
    "title": "The Supreme Temple",
    "subtitle": "The Supreme Temple",
    "image": "https://liketv.oss-cn-hongkong.aliyuncs.com/btfolder2/uploads/20240111/9b137dcf3456e43c891455ed606c9585.png",
    "description": "The Supreme Temple",
    "tags": "",
    "price": 15,
    "vprice": 5,
    "episodes": 80,
    "score": "85",
    "views": "5.07K",
    "favorites": 240,
    "shares": 0,
    "likes": 480,
    "hots": "5.79K",
    "is_favorite": 0,
    "episode_id": 0,
    "view_time": 0,
    "performer_list": [],
    "episodes_list": [
      {
        "track": "https://www.quicktv.vip/uploads/tracklist/20240911/fa853c3f07e7625c72e38e5f1c2cf1753.vtt",
        "id": 463468,
        "vid": 10858,
        "name": "1",
        "image": "https://liketv.oss-cn-hongkong.aliyuncs.com/btfolder2/uploads/20240111/9b137dcf3456e43c891455ed606c9585.png",
        "duration": 91,
        "price": 0,
        "vprice": 0,
        "views": 35,
        "favorites": 10,
        "shares": 0,
        "likes": 18,
        "is_like": 0,
        "url": "https://liketv.oss-cn-hongkong.aliyuncs.com/shendian/1.mp4"
      },
      {
        "track": "https://www.quicktv.vip/uploads/tracklist/20240911/f08f8aed65df7fb9196b72995c8fceda1.vtt",
        "id": 463469,
        "vid": 10858,
        "name": "2",
        "image": "https://liketv.oss-cn-hongkong.aliyuncs.com/btfolder2/uploads/20240111/9b137dcf3456e43c891455ed606c9585.png",
        "duration": 87,
        "price": 0,
        "vprice": 0,
        "views": 28,
        "favorites": 10,
        "shares": 0,
        "likes": 18,
        "is_like": 0,
        "url": "https://liketv.oss-cn-hongkong.aliyuncs.com/shendian/2.mp4"
      },
      {
        "track": "https://www.quicktv.vip/uploads/tracklist/20240911/fa6a62368341f154fcec4187ff02ab79c.vtt",
        "id": 463470,
        "vid": 10858,
        "name": "3",
        "image": "https://liketv.oss-cn-hongkong.aliyuncs.com/btfolder2/uploads/20240111/9b137dcf3456e43c891455ed606c9585.png",
        "duration": 95,
        "price": 0,
        "vprice": 0,
        "views": 28,
        "favorites": 10,
        "shares": 0,
        "likes": 18,
        "is_like": 0,
        "url": "https://liketv.oss-cn-hongkong.aliyuncs.com/shendian/3.mp4"
      },
      {
        "track": "https://www.quicktv.vip/uploads/tracklist/20240911/f2b9d3229dc0885e4984c1ebf619c598a.vtt",
        "id": 463471,
        "vid": 10858,
        "name": "4",
        "image": "https://liketv.oss-cn-hongkong.aliyuncs.com/btfolder2/uploads/20240111/9b137dcf3456e43c891455ed606c9585.png",
        "duration": 80,
        "price": 0,
        "vprice": 0,
        "views": 28,
        "favorites": 10,
        "shares": 0,
        "likes": 18,
        "is_like": 0,
        "url": "https://liketv.oss-cn-hongkong.aliyuncs.com/shendian/4.mp4"
      },
      {
        "track": "https://www.quicktv.vip/uploads/tracklist/20240911/f796331a76c4ad39187cf5be6480215b9.vtt",
        "id": 463472,
        "vid": 10858,
        "name": "5",
        "image": "https://liketv.oss-cn-hongkong.aliyuncs.com/btfolder2/uploads/20240111/9b137dcf3456e43c891455ed606c9585.png",
        "duration": 86,
        "price": 0,
        "vprice": 0,
        "views": 28,
        "favorites": 10,
        "shares": 0,
        "likes": 18,
        "is_like": 0,
        "url": "https://liketv.oss-cn-hongkong.aliyuncs.com/shendian/5.mp4"
      },
      {
        "track": "https://www.quicktv.vip/uploads/tracklist/20240911/ff7a6f911d523b8faa37e7d8875d7d08d.vtt",
        "id": 463473,
        "vid": 10858,
        "name": "6",
        "image": "https://liketv.oss-cn-hongkong.aliyuncs.com/btfolder2/uploads/20240111/9b137dcf3456e43c891455ed606c9585.png",
        "duration": 92,
        "price": 0,
        "vprice": 0,
        "views": 28,
        "favorites": 10,
        "shares": 0,
        "likes": 18,
        "is_like": 0,
        "url": "https://liketv.oss-cn-hongkong.aliyuncs.com/shendian/6.mp4"
      },
      {
        "track": "https://www.quicktv.vip/uploads/tracklist/20240911/ff2c8dd953ecdf05435d8888998d786c7.vtt",
        "id": 463474,
        "vid": 10858,
        "name": "7",
        "image": "https://liketv.oss-cn-hongkong.aliyuncs.com/btfolder2/uploads/20240111/9b137dcf3456e43c891455ed606c9585.png",
        "duration": 83,
        "price": 0,
        "vprice": 0,
        "views": 28,
        "favorites": 10,
        "shares": 0,
        "likes": 18,
        "is_like": 0,
        "url": "https://liketv.oss-cn-hongkong.aliyuncs.com/shendian/7.mp4"
      },
      {
        "track": "https://www.quicktv.vip/uploads/tracklist/20240911/f0369a5c2c9bba55e80b9115a5b2473b7.vtt",
        "id": 463475,
        "vid": 10858,
        "name": "8",
        "image": "https://liketv.oss-cn-hongkong.aliyuncs.com/btfolder2/uploads/20240111/9b137dcf3456e43c891455ed606c9585.png",
        "duration": 83,
        "price": 0,
        "vprice": 0,
        "views": 28,
        "favorites": 10,
        "shares": 0,
        "likes": 18,
        "is_like": 0,
        "url": "https://liketv.oss-cn-hongkong.aliyuncs.com/shendian/8.mp4"
      },
      {
        "track": "https://www.quicktv.vip/uploads/tracklist/20240911/f5027f7a26a9666d68702fd84a12f734a.vtt",
        "id": 463476,
        "vid": 10858,
        "name": "9",
        "image": "https://liketv.oss-cn-hongkong.aliyuncs.com/btfolder2/uploads/20240111/9b137dcf3456e43c891455ed606c9585.png",
        "duration": 86,
        "price": 0,
        "vprice": 0,
        "views": 28,
        "favorites": 10,
        "shares": 0,
        "likes": 18,
        "is_like": 0,
        "url": "https://liketv.oss-cn-hongkong.aliyuncs.com/shendian/9.mp4"
      },
      {
        "track": "https://www.quicktv.vip/uploads/tracklist/20240911/fcd225425a5f280a70e77c6fb3615160c.vtt",
        "id": 463477,
        "vid": 10858,
        "name": "10",
        "image": "https://liketv.oss-cn-hongkong.aliyuncs.com/btfolder2/uploads/20240111/9b137dcf3456e43c891455ed606c9585.png",
        "duration": 93,
        "price": 0,
        "vprice": 0,
        "views": 28,
        "favorites": 10,
        "shares": 0,
        "likes": 18,
        "is_like": 0,
        "url": "https://liketv.oss-cn-hongkong.aliyuncs.com/shendian/10.mp4"
      },
      {
        "track": "https://www.quicktv.vip/uploads/tracklist/20240911/f4681a8fbcf112258b689a56c31c83ef6.vtt",
        "id": 463478,
        "vid": 10858,
        "name": "11",
        "image": "https://liketv.oss-cn-hongkong.aliyuncs.com/btfolder2/uploads/20240111/9b137dcf3456e43c891455ed606c9585.png",
        "duration": 95,
        "price": 10,
        "vprice": 1,
        "views": 28,
        "favorites": 10,
        "shares": 0,
        "likes": 18,
        "is_like": 0,
        "url": "https://liketv.oss-cn-hongkong.aliyuncs.com/shendian/11.mp4"
      },
      {
        "track": "https://www.quicktv.vip/uploads/tracklist/20240911/fdd63d991801377037958e1d3a4343830.vtt",
        "id": 463479,
        "vid": 10858,
        "name": "12",
        "image": "https://liketv.oss-cn-hongkong.aliyuncs.com/btfolder2/uploads/20240111/9b137dcf3456e43c891455ed606c9585.png",
        "duration": 86,
        "price": 10,
        "vprice": 1,
        "views": 28,
        "favorites": 10,
        "shares": 0,
        "likes": 18,
        "is_like": 0,
        "url": "https://liketv.oss-cn-hongkong.aliyuncs.com/shendian/12.mp4"
      },
      {
        "track": "https://www.quicktv.vip/uploads/tracklist/20240911/f1d4fbc05e5dfa8f2519c4abc73368201.vtt",
        "id": 463480,
        "vid": 10858,
        "name": "13",
        "image": "https://liketv.oss-cn-hongkong.aliyuncs.com/btfolder2/uploads/20240111/9b137dcf3456e43c891455ed606c9585.png",
        "duration": 88,
        "price": 10,
        "vprice": 1,
        "views": 28,
        "favorites": 10,
        "shares": 0,
        "likes": 18,
        "is_like": 0,
        "url": "https://liketv.oss-cn-hongkong.aliyuncs.com/shendian/13.mp4"
      },
      {
        "track": "https://www.quicktv.vip/uploads/tracklist/20240911/fc0839a0d83a62b6566f5a26b579ff212.vtt",
        "id": 463481,
        "vid": 10858,
        "name": "14",
        "image": "https://liketv.oss-cn-hongkong.aliyuncs.com/btfolder2/uploads/20240111/9b137dcf3456e43c891455ed606c9585.png",
        "duration": 86,
        "price": 10,
        "vprice": 1,
        "views": 28,
        "favorites": 10,
        "shares": 0,
        "likes": 18,
        "is_like": 0,
        "url": "https://liketv.oss-cn-hongkong.aliyuncs.com/shendian/14.mp4"
      },
      {
        "track": "https://www.quicktv.vip/uploads/tracklist/20240911/f92b792b5193ebea8a175e517af5d0f8d.vtt",
        "id": 463482,
        "vid": 10858,
        "name": "15",
        "image": "https://liketv.oss-cn-hongkong.aliyuncs.com/btfolder2/uploads/20240111/9b137dcf3456e43c891455ed606c9585.png",
        "duration": 79,
        "price": 10,
        "vprice": 1,
        "views": 28,
        "favorites": 10,
        "shares": 0,
        "likes": 18,
        "is_like": 0,
        "url": "https://liketv.oss-cn-hongkong.aliyuncs.com/shendian/15.mp4"
      },
      {
        "track": "https://www.quicktv.vip/uploads/tracklist/20240911/f1801b1e9cce28ab45cc0fd7823014add.vtt",
        "id": 463483,
        "vid": 10858,
        "name": "16",
        "image": "https://liketv.oss-cn-hongkong.aliyuncs.com/btfolder2/uploads/20240111/9b137dcf3456e43c891455ed606c9585.png",
        "duration": 89,
        "price": 10,
        "vprice": 1,
        "views": 28,
        "favorites": 10,
        "shares": 0,
        "likes": 18,
        "is_like": 0,
        "url": "https://liketv.oss-cn-hongkong.aliyuncs.com/shendian/16.mp4"
      },
      {
        "track": "https://www.quicktv.vip/uploads/tracklist/20240911/f2c21733bc28c0e0ee1f85e5d6d4b3e2a.vtt",
        "id": 463484,
        "vid": 10858,
        "name": "17",
        "image": "https://liketv.oss-cn-hongkong.aliyuncs.com/btfolder2/uploads/20240111/9b137dcf3456e43c891455ed606c9585.png",
        "duration": 83,
        "price": 10,
        "vprice": 1,
        "views": 28,
        "favorites": 10,
        "shares": 0,
        "likes": 18,
        "is_like": 0,
        "url": "https://liketv.oss-cn-hongkong.aliyuncs.com/shendian/17.mp4"
      },
      {
        "track": "https://www.quicktv.vip/uploads/tracklist/20240911/f2f8df855e511c69ac1a4b8a1bc100f11.vtt",
        "id": 463485,
        "vid": 10858,
        "name": "18",
        "image": "https://liketv.oss-cn-hongkong.aliyuncs.com/btfolder2/uploads/20240111/9b137dcf3456e43c891455ed606c9585.png",
        "duration": 92,
        "price": 10,
        "vprice": 1,
        "views": 28,
        "favorites": 10,
        "shares": 0,
        "likes": 18,
        "is_like": 0,
        "url": "https://liketv.oss-cn-hongkong.aliyuncs.com/shendian/18.mp4"
      },
      {
        "track": "https://www.quicktv.vip/uploads/tracklist/20240911/ff5cfd7e369ee4f21ef20caaa68f1fe57.vtt",
        "id": 463486,
        "vid": 10858,
        "name": "19",
        "image": "https://liketv.oss-cn-hongkong.aliyuncs.com/btfolder2/uploads/20240111/9b137dcf3456e43c891455ed606c9585.png",
        "duration": 89,
        "price": 10,
        "vprice": 1,
        "views": 28,
        "favorites": 10,
        "shares": 0,
        "likes": 18,
        "is_like": 0,
        "url": "https://liketv.oss-cn-hongkong.aliyuncs.com/shendian/19.mp4"
      },
      {
        "track": "https://www.quicktv.vip/uploads/tracklist/20240911/fd00a850b678f27907681c0f03616ed38.vtt",
        "id": 463487,
        "vid": 10858,
        "name": "20",
        "image": "https://liketv.oss-cn-hongkong.aliyuncs.com/btfolder2/uploads/20240111/9b137dcf3456e43c891455ed606c9585.png",
        "duration": 95,
        "price": 10,
        "vprice": 1,
        "views": 28,
        "favorites": 10,
        "shares": 0,
        "likes": 18,
        "is_like": 0,
        "url": "https://liketv.oss-cn-hongkong.aliyuncs.com/shendian/20.mp4"
      },
      {
        "track": "https://www.quicktv.vip/uploads/tracklist/20240911/f728743beaf0b13326c49e2bd05f1070a.vtt",
        "id": 463488,
        "vid": 10858,
        "name": "21",
        "image": "https://liketv.oss-cn-hongkong.aliyuncs.com/btfolder2/uploads/20240111/9b137dcf3456e43c891455ed606c9585.png",
        "duration": 79,
        "price": 10,
        "vprice": 1,
        "views": 28,
        "favorites": 10,
        "shares": 0,
        "likes": 18,
        "is_like": 0,
        "url": "https://liketv.oss-cn-hongkong.aliyuncs.com/shendian/21.mp4"
      },
      {
        "track": "https://www.quicktv.vip/uploads/tracklist/20240911/fcefa37deef19e606dd9046a59f906934.vtt",
        "id": 463489,
        "vid": 10858,
        "name": "22",
        "image": "https://liketv.oss-cn-hongkong.aliyuncs.com/btfolder2/uploads/20240111/9b137dcf3456e43c891455ed606c9585.png",
        "duration": 86,
        "price": 10,
        "vprice": 1,
        "views": 28,
        "favorites": 10,
        "shares": 0,
        "likes": 18,
        "is_like": 0,
        "url": "https://liketv.oss-cn-hongkong.aliyuncs.com/shendian/22.mp4"
      },
      {
        "track": "https://www.quicktv.vip/uploads/tracklist/20240911/f530578ca83dc4380d410186d6cf80dde.vtt",
        "id": 463490,
        "vid": 10858,
        "name": "23",
        "image": "https://liketv.oss-cn-hongkong.aliyuncs.com/btfolder2/uploads/20240111/9b137dcf3456e43c891455ed606c9585.png",
        "duration": 86,
        "price": 10,
        "vprice": 1,
        "views": 28,
        "favorites": 10,
        "shares": 0,
        "likes": 18,
        "is_like": 0,
        "url": "https://liketv.oss-cn-hongkong.aliyuncs.com/shendian/23.mp4"
      },
      {
        "track": "https://www.quicktv.vip/uploads/tracklist/20240911/f4dff777a411178fd5bb1f644aa152c7d.vtt",
        "id": 463491,
        "vid": 10858,
        "name": "24",
        "image": "https://liketv.oss-cn-hongkong.aliyuncs.com/btfolder2/uploads/20240111/9b137dcf3456e43c891455ed606c9585.png",
        "duration": 94,
        "price": 10,
        "vprice": 1,
        "views": 28,
        "favorites": 10,
        "shares": 0,
        "likes": 18,
        "is_like": 0,
        "url": "https://liketv.oss-cn-hongkong.aliyuncs.com/shendian/24.mp4"
      },
      {
        "track": "https://www.quicktv.vip/uploads/tracklist/20240911/f4a66e98e245790c762c1015787b34c88.vtt",
        "id": 463492,
        "vid": 10858,
        "name": "25",
        "image": "https://liketv.oss-cn-hongkong.aliyuncs.com/btfolder2/uploads/20240111/9b137dcf3456e43c891455ed606c9585.png",
        "duration": 84,
        "price": 10,
        "vprice": 1,
        "views": 28,
        "favorites": 10,
        "shares": 0,
        "likes": 18,
        "is_like": 0,
        "url": "https://liketv.oss-cn-hongkong.aliyuncs.com/shendian/25.mp4"
      },
      {
        "track": "https://www.quicktv.vip/uploads/tracklist/20240911/f97b2c5f630363130acbff543e6161a04.vtt",
        "id": 463493,
        "vid": 10858,
        "name": "26",
        "image": "https://liketv.oss-cn-hongkong.aliyuncs.com/btfolder2/uploads/20240111/9b137dcf3456e43c891455ed606c9585.png",
        "duration": 90,
        "price": 10,
        "vprice": 1,
        "views": 28,
        "favorites": 10,
        "shares": 0,
        "likes": 18,
        "is_like": 0,
        "url": "https://liketv.oss-cn-hongkong.aliyuncs.com/shendian/26.mp4"
      },
      {
        "track": "https://www.quicktv.vip/uploads/tracklist/20240911/fe6119e7f63e69e7a0ba14a9544e03660.vtt",
        "id": 463494,
        "vid": 10858,
        "name": "27",
        "image": "https://liketv.oss-cn-hongkong.aliyuncs.com/btfolder2/uploads/20240111/9b137dcf3456e43c891455ed606c9585.png",
        "duration": 92,
        "price": 10,
        "vprice": 1,
        "views": 28,
        "favorites": 10,
        "shares": 0,
        "likes": 18,
        "is_like": 0,
        "url": "https://liketv.oss-cn-hongkong.aliyuncs.com/shendian/27.mp4"
      },
      {
        "track": "https://www.quicktv.vip/uploads/tracklist/20240911/fd02bdfeee59f2d882d26a2f04e9b2445.vtt",
        "id": 463495,
        "vid": 10858,
        "name": "28",
        "image": "https://liketv.oss-cn-hongkong.aliyuncs.com/btfolder2/uploads/20240111/9b137dcf3456e43c891455ed606c9585.png",
        "duration": 83,
        "price": 10,
        "vprice": 1,
        "views": 28,
        "favorites": 10,
        "shares": 0,
        "likes": 18,
        "is_like": 0,
        "url": "https://liketv.oss-cn-hongkong.aliyuncs.com/shendian/28.mp4"
      },
      {
        "track": "https://www.quicktv.vip/uploads/tracklist/20240911/f252f235f12fa0d434aa1456dafd60e3d.vtt",
        "id": 463496,
        "vid": 10858,
        "name": "29",
        "image": "https://liketv.oss-cn-hongkong.aliyuncs.com/btfolder2/uploads/20240111/9b137dcf3456e43c891455ed606c9585.png",
        "duration": 88,
        "price": 10,
        "vprice": 1,
        "views": 28,
        "favorites": 10,
        "shares": 0,
        "likes": 18,
        "is_like": 0,
        "url": "https://liketv.oss-cn-hongkong.aliyuncs.com/shendian/29.mp4"
      },
      {
        "track": "https://www.quicktv.vip/uploads/tracklist/20240911/ffe88bacaf2210431eab630d89d792905.vtt",
        "id": 463497,
        "vid": 10858,
        "name": "30",
        "image": "https://liketv.oss-cn-hongkong.aliyuncs.com/btfolder2/uploads/20240111/9b137dcf3456e43c891455ed606c9585.png",
        "duration": 86,
        "price": 10,
        "vprice": 1,
        "views": 28,
        "favorites": 10,
        "shares": 0,
        "likes": 18,
        "is_like": 0,
        "url": "https://liketv.oss-cn-hongkong.aliyuncs.com/shendian/30.mp4"
      },
      {
        "track": "https://www.quicktv.vip/uploads/tracklist/20240911/f2b17ff956108e5338256bd30272b08ec.vtt",
        "id": 463498,
        "vid": 10858,
        "name": "31",
        "image": "https://liketv.oss-cn-hongkong.aliyuncs.com/btfolder2/uploads/20240111/9b137dcf3456e43c891455ed606c9585.png",
        "duration": 90,
        "price": 10,
        "vprice": 1,
        "views": 28,
        "favorites": 10,
        "shares": 0,
        "likes": 18,
        "is_like": 0,
        "url": "https://liketv.oss-cn-hongkong.aliyuncs.com/shendian/31.mp4"
      },
      {
        "track": "https://www.quicktv.vip/uploads/tracklist/20240911/fba496b2018bc0279bc1f0c8865837bba.vtt",
        "id": 463499,
        "vid": 10858,
        "name": "32",
        "image": "https://liketv.oss-cn-hongkong.aliyuncs.com/btfolder2/uploads/20240111/9b137dcf3456e43c891455ed606c9585.png",
        "duration": 79,
        "price": 10,
        "vprice": 1,
        "views": 28,
        "favorites": 10,
        "shares": 0,
        "likes": 18,
        "is_like": 0,
        "url": "https://liketv.oss-cn-hongkong.aliyuncs.com/shendian/32.mp4"
      },
      {
        "track": "https://www.quicktv.vip/uploads/tracklist/20240911/fff397777419f6d55ddacf4d120eb443b.vtt",
        "id": 463500,
        "vid": 10858,
        "name": "33",
        "image": "https://liketv.oss-cn-hongkong.aliyuncs.com/btfolder2/uploads/20240111/9b137dcf3456e43c891455ed606c9585.png",
        "duration": 94,
        "price": 10,
        "vprice": 1,
        "views": 28,
        "favorites": 10,
        "shares": 0,
        "likes": 18,
        "is_like": 0,
        "url": "https://liketv.oss-cn-hongkong.aliyuncs.com/shendian/33.mp4"
      },
      {
        "track": "https://www.quicktv.vip/uploads/tracklist/20240911/faad7e7c0a194b323f8cf4b2b8ac94d6d.vtt",
        "id": 463501,
        "vid": 10858,
        "name": "34",
        "image": "https://liketv.oss-cn-hongkong.aliyuncs.com/btfolder2/uploads/20240111/9b137dcf3456e43c891455ed606c9585.png",
        "duration": 88,
        "price": 10,
        "vprice": 1,
        "views": 28,
        "favorites": 10,
        "shares": 0,
        "likes": 18,
        "is_like": 0,
        "url": "https://liketv.oss-cn-hongkong.aliyuncs.com/shendian/34.mp4"
      },
      {
        "track": "https://www.quicktv.vip/uploads/tracklist/20240911/fc4499e788a2a6669eef57941061d2eff.vtt",
        "id": 463502,
        "vid": 10858,
        "name": "35",
        "image": "https://liketv.oss-cn-hongkong.aliyuncs.com/btfolder2/uploads/20240111/9b137dcf3456e43c891455ed606c9585.png",
        "duration": 86,
        "price": 10,
        "vprice": 1,
        "views": 28,
        "favorites": 10,
        "shares": 0,
        "likes": 18,
        "is_like": 0,
        "url": "https://liketv.oss-cn-hongkong.aliyuncs.com/shendian/35.mp4"
      },
      {
        "track": "https://www.quicktv.vip/uploads/tracklist/20240911/fc7b82e159eba272cc8b42470a8f74bc9.vtt",
        "id": 463503,
        "vid": 10858,
        "name": "36",
        "image": "https://liketv.oss-cn-hongkong.aliyuncs.com/btfolder2/uploads/20240111/9b137dcf3456e43c891455ed606c9585.png",
        "duration": 80,
        "price": 10,
        "vprice": 1,
        "views": 28,
        "favorites": 10,
        "shares": 0,
        "likes": 18,
        "is_like": 0,
        "url": "https://liketv.oss-cn-hongkong.aliyuncs.com/shendian/36.mp4"
      },
      {
        "track": "https://www.quicktv.vip/uploads/tracklist/20240911/f292be3ac63e0cc7202b1a74cbedd1b64.vtt",
        "id": 463504,
        "vid": 10858,
        "name": "37",
        "image": "https://liketv.oss-cn-hongkong.aliyuncs.com/btfolder2/uploads/20240111/9b137dcf3456e43c891455ed606c9585.png",
        "duration": 83,
        "price": 10,
        "vprice": 1,
        "views": 28,
        "favorites": 10,
        "shares": 0,
        "likes": 18,
        "is_like": 0,
        "url": "https://liketv.oss-cn-hongkong.aliyuncs.com/shendian/37.mp4"
      },
      {
        "track": "https://www.quicktv.vip/uploads/tracklist/20240911/f18c12ee842aa30310f88b4fbca631a0a.vtt",
        "id": 463505,
        "vid": 10858,
        "name": "38",
        "image": "https://liketv.oss-cn-hongkong.aliyuncs.com/btfolder2/uploads/20240111/9b137dcf3456e43c891455ed606c9585.png",
        "duration": 93,
        "price": 10,
        "vprice": 1,
        "views": 28,
        "favorites": 10,
        "shares": 0,
        "likes": 18,
        "is_like": 0,
        "url": "https://liketv.oss-cn-hongkong.aliyuncs.com/shendian/38.mp4"
      },
      {
        "track": "https://www.quicktv.vip/uploads/tracklist/20240911/f943b16d71d813c8f8e19a623d615344a.vtt",
        "id": 463506,
        "vid": 10858,
        "name": "39",
        "image": "https://liketv.oss-cn-hongkong.aliyuncs.com/btfolder2/uploads/20240111/9b137dcf3456e43c891455ed606c9585.png",
        "duration": 82,
        "price": 10,
        "vprice": 1,
        "views": 28,
        "favorites": 10,
        "shares": 0,
        "likes": 18,
        "is_like": 0,
        "url": "https://liketv.oss-cn-hongkong.aliyuncs.com/shendian/39.mp4"
      },
      {
        "track": "https://www.quicktv.vip/uploads/tracklist/20240911/fa31e0ed7a99114542f99aaeed011851d.vtt",
        "id": 463507,
        "vid": 10858,
        "name": "40",
        "image": "https://liketv.oss-cn-hongkong.aliyuncs.com/btfolder2/uploads/20240111/9b137dcf3456e43c891455ed606c9585.png",
        "duration": 86,
        "price": 10,
        "vprice": 1,
        "views": 28,
        "favorites": 10,
        "shares": 0,
        "likes": 18,
        "is_like": 0,
        "url": "https://liketv.oss-cn-hongkong.aliyuncs.com/shendian/40.mp4"
      },
      {
        "track": "https://www.quicktv.vip/uploads/tracklist/20240911/f348ac0bfa7b147082fd5dad3321993e7.vtt",
        "id": 463508,
        "vid": 10858,
        "name": "41",
        "image": "https://liketv.oss-cn-hongkong.aliyuncs.com/btfolder2/uploads/20240111/9b137dcf3456e43c891455ed606c9585.png",
        "duration": 89,
        "price": 10,
        "vprice": 1,
        "views": 28,
        "favorites": 10,
        "shares": 0,
        "likes": 18,
        "is_like": 0,
        "url": "https://liketv.oss-cn-hongkong.aliyuncs.com/shendian/41.mp4"
      },
      {
        "track": "https://www.quicktv.vip/uploads/tracklist/20240911/f54e68f6b33f07b3748045571f81dd76e.vtt",
        "id": 463509,
        "vid": 10858,
        "name": "42",
        "image": "https://liketv.oss-cn-hongkong.aliyuncs.com/btfolder2/uploads/20240111/9b137dcf3456e43c891455ed606c9585.png",
        "duration": 84,
        "price": 10,
        "vprice": 1,
        "views": 28,
        "favorites": 10,
        "shares": 0,
        "likes": 18,
        "is_like": 0,
        "url": "https://liketv.oss-cn-hongkong.aliyuncs.com/shendian/42.mp4"
      },
      {
        "track": "https://www.quicktv.vip/uploads/tracklist/20240911/f7fccfd2a3a5d75eb10e71126aaaaa65b.vtt",
        "id": 463510,
        "vid": 10858,
        "name": "43",
        "image": "https://liketv.oss-cn-hongkong.aliyuncs.com/btfolder2/uploads/20240111/9b137dcf3456e43c891455ed606c9585.png",
        "duration": 84,
        "price": 10,
        "vprice": 1,
        "views": 28,
        "favorites": 10,
        "shares": 0,
        "likes": 18,
        "is_like": 0,
        "url": "https://liketv.oss-cn-hongkong.aliyuncs.com/shendian/43.mp4"
      },
      {
        "track": "https://www.quicktv.vip/uploads/tracklist/20240911/fc0f4653f5cd4668040e7123d7fa0b06c.vtt",
        "id": 463511,
        "vid": 10858,
        "name": "44",
        "image": "https://liketv.oss-cn-hongkong.aliyuncs.com/btfolder2/uploads/20240111/9b137dcf3456e43c891455ed606c9585.png",
        "duration": 93,
        "price": 10,
        "vprice": 1,
        "views": 28,
        "favorites": 10,
        "shares": 0,
        "likes": 18,
        "is_like": 0,
        "url": "https://liketv.oss-cn-hongkong.aliyuncs.com/shendian/44.mp4"
      },
      {
        "track": "https://www.quicktv.vip/uploads/tracklist/20240911/f113530e4f31d92aebd170fe51ee02165.vtt",
        "id": 463512,
        "vid": 10858,
        "name": "45",
        "image": "https://liketv.oss-cn-hongkong.aliyuncs.com/btfolder2/uploads/20240111/9b137dcf3456e43c891455ed606c9585.png",
        "duration": 86,
        "price": 10,
        "vprice": 1,
        "views": 28,
        "favorites": 10,
        "shares": 0,
        "likes": 18,
        "is_like": 0,
        "url": "https://liketv.oss-cn-hongkong.aliyuncs.com/shendian/45.mp4"
      },
      {
        "track": "https://www.quicktv.vip/uploads/tracklist/20240911/f449f06adc6e6f2b2a011bf629254247c.vtt",
        "id": 463513,
        "vid": 10858,
        "name": "46",
        "image": "https://liketv.oss-cn-hongkong.aliyuncs.com/btfolder2/uploads/20240111/9b137dcf3456e43c891455ed606c9585.png",
        "duration": 90,
        "price": 10,
        "vprice": 1,
        "views": 28,
        "favorites": 10,
        "shares": 0,
        "likes": 18,
        "is_like": 0,
        "url": "https://liketv.oss-cn-hongkong.aliyuncs.com/shendian/46.mp4"
      },
      {
        "track": "https://www.quicktv.vip/uploads/tracklist/20240911/fa08559bd40597ebb0c4dcb19e2ec9f5a.vtt",
        "id": 463514,
        "vid": 10858,
        "name": "47",
        "image": "https://liketv.oss-cn-hongkong.aliyuncs.com/btfolder2/uploads/20240111/9b137dcf3456e43c891455ed606c9585.png",
        "duration": 82,
        "price": 10,
        "vprice": 1,
        "views": 28,
        "favorites": 10,
        "shares": 0,
        "likes": 18,
        "is_like": 0,
        "url": "https://liketv.oss-cn-hongkong.aliyuncs.com/shendian/47.mp4"
      },
      {
        "track": "https://www.quicktv.vip/uploads/tracklist/20240911/fc59798d482d5a81d9a4219046cb63db0.vtt",
        "id": 463515,
        "vid": 10858,
        "name": "48",
        "image": "https://liketv.oss-cn-hongkong.aliyuncs.com/btfolder2/uploads/20240111/9b137dcf3456e43c891455ed606c9585.png",
        "duration": 87,
        "price": 10,
        "vprice": 1,
        "views": 28,
        "favorites": 10,
        "shares": 0,
        "likes": 18,
        "is_like": 0,
        "url": "https://liketv.oss-cn-hongkong.aliyuncs.com/shendian/48.mp4"
      },
      {
        "track": "https://www.quicktv.vip/uploads/tracklist/20240911/fbe640c1a08006c95633a2c5ac6bd89ae.vtt",
        "id": 463516,
        "vid": 10858,
        "name": "49",
        "image": "https://liketv.oss-cn-hongkong.aliyuncs.com/btfolder2/uploads/20240111/9b137dcf3456e43c891455ed606c9585.png",
        "duration": 90,
        "price": 10,
        "vprice": 1,
        "views": 28,
        "favorites": 10,
        "shares": 0,
        "likes": 18,
        "is_like": 0,
        "url": "https://liketv.oss-cn-hongkong.aliyuncs.com/shendian/49.mp4"
      },
      {
        "track": "https://www.quicktv.vip/uploads/tracklist/20240911/fbfbdb01c34a6202d70b83ba92c30adfc.vtt",
        "id": 463517,
        "vid": 10858,
        "name": "50",
        "image": "https://liketv.oss-cn-hongkong.aliyuncs.com/btfolder2/uploads/20240111/9b137dcf3456e43c891455ed606c9585.png",
        "duration": 92,
        "price": 10,
        "vprice": 1,
        "views": 28,
        "favorites": 10,
        "shares": 0,
        "likes": 18,
        "is_like": 0,
        "url": "https://liketv.oss-cn-hongkong.aliyuncs.com/shendian/50.mp4"
      },
      {
        "track": "https://www.quicktv.vip/uploads/tracklist/20240911/fbda23b9c010282dc5bf97f0d9c883fbf.vtt",
        "id": 463518,
        "vid": 10858,
        "name": "51",
        "image": "https://liketv.oss-cn-hongkong.aliyuncs.com/btfolder2/uploads/20240111/9b137dcf3456e43c891455ed606c9585.png",
        "duration": 91,
        "price": 10,
        "vprice": 1,
        "views": 28,
        "favorites": 10,
        "shares": 0,
        "likes": 18,
        "is_like": 0,
        "url": "https://liketv.oss-cn-hongkong.aliyuncs.com/shendian/51.mp4"
      },
      {
        "track": "https://www.quicktv.vip/uploads/tracklist/20240911/f5e4d102f948c56a7f06f69632b3e8f7a.vtt",
        "id": 463519,
        "vid": 10858,
        "name": "52",
        "image": "https://liketv.oss-cn-hongkong.aliyuncs.com/btfolder2/uploads/20240111/9b137dcf3456e43c891455ed606c9585.png",
        "duration": 85,
        "price": 10,
        "vprice": 1,
        "views": 28,
        "favorites": 10,
        "shares": 0,
        "likes": 18,
        "is_like": 0,
        "url": "https://liketv.oss-cn-hongkong.aliyuncs.com/shendian/52.mp4"
      },
      {
        "track": "https://www.quicktv.vip/uploads/tracklist/20240911/f0b3608f254f07c4fd1bac0a0fc08a586.vtt",
        "id": 463520,
        "vid": 10858,
        "name": "53",
        "image": "https://liketv.oss-cn-hongkong.aliyuncs.com/btfolder2/uploads/20240111/9b137dcf3456e43c891455ed606c9585.png",
        "duration": 91,
        "price": 10,
        "vprice": 1,
        "views": 28,
        "favorites": 10,
        "shares": 0,
        "likes": 18,
        "is_like": 0,
        "url": "https://liketv.oss-cn-hongkong.aliyuncs.com/shendian/53.mp4"
      },
      {
        "track": "https://www.quicktv.vip/uploads/tracklist/20240911/fe86ac3fc50eee3dc6bd81e838038ab9f.vtt",
        "id": 463521,
        "vid": 10858,
        "name": "54",
        "image": "https://liketv.oss-cn-hongkong.aliyuncs.com/btfolder2/uploads/20240111/9b137dcf3456e43c891455ed606c9585.png",
        "duration": 84,
        "price": 10,
        "vprice": 1,
        "views": 28,
        "favorites": 10,
        "shares": 0,
        "likes": 18,
        "is_like": 0,
        "url": "https://liketv.oss-cn-hongkong.aliyuncs.com/shendian/54.mp4"
      },
      {
        "track": "https://www.quicktv.vip/uploads/tracklist/20240911/fcd661bc504ae89a34baaf8b8c4530ae8.vtt",
        "id": 463522,
        "vid": 10858,
        "name": "55",
        "image": "https://liketv.oss-cn-hongkong.aliyuncs.com/btfolder2/uploads/20240111/9b137dcf3456e43c891455ed606c9585.png",
        "duration": 95,
        "price": 10,
        "vprice": 1,
        "views": 28,
        "favorites": 10,
        "shares": 0,
        "likes": 18,
        "is_like": 0,
        "url": "https://liketv.oss-cn-hongkong.aliyuncs.com/shendian/55.mp4"
      },
      {
        "track": "https://www.quicktv.vip/uploads/tracklist/20240911/fd6028acc04cd1cea7385397871f47ee7.vtt",
        "id": 463523,
        "vid": 10858,
        "name": "56",
        "image": "https://liketv.oss-cn-hongkong.aliyuncs.com/btfolder2/uploads/20240111/9b137dcf3456e43c891455ed606c9585.png",
        "duration": 80,
        "price": 10,
        "vprice": 1,
        "views": 28,
        "favorites": 10,
        "shares": 0,
        "likes": 18,
        "is_like": 0,
        "url": "https://liketv.oss-cn-hongkong.aliyuncs.com/shendian/56.mp4"
      },
      {
        "track": "https://www.quicktv.vip/uploads/tracklist/20240911/fe245fc179822815366c3b378c20da383.vtt",
        "id": 463524,
        "vid": 10858,
        "name": "57",
        "image": "https://liketv.oss-cn-hongkong.aliyuncs.com/btfolder2/uploads/20240111/9b137dcf3456e43c891455ed606c9585.png",
        "duration": 83,
        "price": 10,
        "vprice": 1,
        "views": 28,
        "favorites": 10,
        "shares": 0,
        "likes": 18,
        "is_like": 0,
        "url": "https://liketv.oss-cn-hongkong.aliyuncs.com/shendian/57.mp4"
      },
      {
        "track": "https://www.quicktv.vip/uploads/tracklist/20240911/fbd6d5cc3550c2deebc856f886bcba645.vtt",
        "id": 463525,
        "vid": 10858,
        "name": "58",
        "image": "https://liketv.oss-cn-hongkong.aliyuncs.com/btfolder2/uploads/20240111/9b137dcf3456e43c891455ed606c9585.png",
        "duration": 80,
        "price": 10,
        "vprice": 1,
        "views": 28,
        "favorites": 10,
        "shares": 0,
        "likes": 18,
        "is_like": 0,
        "url": "https://liketv.oss-cn-hongkong.aliyuncs.com/shendian/58.mp4"
      },
      {
        "track": "https://www.quicktv.vip/uploads/tracklist/20240911/ff31007a65664e684d8e31034715e799d.vtt",
        "id": 463526,
        "vid": 10858,
        "name": "59",
        "image": "https://liketv.oss-cn-hongkong.aliyuncs.com/btfolder2/uploads/20240111/9b137dcf3456e43c891455ed606c9585.png",
        "duration": 93,
        "price": 10,
        "vprice": 1,
        "views": 28,
        "favorites": 10,
        "shares": 0,
        "likes": 18,
        "is_like": 0,
        "url": "https://liketv.oss-cn-hongkong.aliyuncs.com/shendian/59.mp4"
      },
      {
        "track": "https://www.quicktv.vip/uploads/tracklist/20240911/f6c6cc8de9831f34e27c823376952880d.vtt",
        "id": 463527,
        "vid": 10858,
        "name": "60",
        "image": "https://liketv.oss-cn-hongkong.aliyuncs.com/btfolder2/uploads/20240111/9b137dcf3456e43c891455ed606c9585.png",
        "duration": 93,
        "price": 10,
        "vprice": 1,
        "views": 28,
        "favorites": 10,
        "shares": 0,
        "likes": 18,
        "is_like": 0,
        "url": "https://liketv.oss-cn-hongkong.aliyuncs.com/shendian/60.mp4"
      },
      {
        "track": "https://www.quicktv.vip/uploads/tracklist/20240911/fa5c85424c5ac2ca1666fe70c4c5cec30.vtt",
        "id": 463528,
        "vid": 10858,
        "name": "61",
        "image": "https://liketv.oss-cn-hongkong.aliyuncs.com/btfolder2/uploads/20240111/9b137dcf3456e43c891455ed606c9585.png",
        "duration": 81,
        "price": 10,
        "vprice": 1,
        "views": 28,
        "favorites": 10,
        "shares": 0,
        "likes": 18,
        "is_like": 0,
        "url": "https://liketv.oss-cn-hongkong.aliyuncs.com/shendian/61.mp4"
      },
      {
        "track": "https://www.quicktv.vip/uploads/tracklist/20240911/f88136aba787eb7a1519fe6a1d66f7e92.vtt",
        "id": 463529,
        "vid": 10858,
        "name": "62",
        "image": "https://liketv.oss-cn-hongkong.aliyuncs.com/btfolder2/uploads/20240111/9b137dcf3456e43c891455ed606c9585.png",
        "duration": 79,
        "price": 10,
        "vprice": 1,
        "views": 28,
        "favorites": 10,
        "shares": 0,
        "likes": 18,
        "is_like": 0,
        "url": "https://liketv.oss-cn-hongkong.aliyuncs.com/shendian/62.mp4"
      },
      {
        "track": "https://www.quicktv.vip/uploads/tracklist/20240911/f4394980aebbdb54384a2884739447d03.vtt",
        "id": 463530,
        "vid": 10858,
        "name": "63",
        "image": "https://liketv.oss-cn-hongkong.aliyuncs.com/btfolder2/uploads/20240111/9b137dcf3456e43c891455ed606c9585.png",
        "duration": 90,
        "price": 10,
        "vprice": 1,
        "views": 28,
        "favorites": 10,
        "shares": 0,
        "likes": 18,
        "is_like": 0,
        "url": "https://liketv.oss-cn-hongkong.aliyuncs.com/shendian/63.mp4"
      },
      {
        "track": "https://www.quicktv.vip/uploads/tracklist/20240911/fe74446af377350f77c7ea8cc1de64c44.vtt",
        "id": 463531,
        "vid": 10858,
        "name": "64",
        "image": "https://liketv.oss-cn-hongkong.aliyuncs.com/btfolder2/uploads/20240111/9b137dcf3456e43c891455ed606c9585.png",
        "duration": 91,
        "price": 10,
        "vprice": 1,
        "views": 28,
        "favorites": 10,
        "shares": 0,
        "likes": 18,
        "is_like": 0,
        "url": "https://liketv.oss-cn-hongkong.aliyuncs.com/shendian/64.mp4"
      },
      {
        "track": "https://www.quicktv.vip/uploads/tracklist/20240911/fe98eb3feba510b884850175fe531ca40.vtt",
        "id": 463532,
        "vid": 10858,
        "name": "65",
        "image": "https://liketv.oss-cn-hongkong.aliyuncs.com/btfolder2/uploads/20240111/9b137dcf3456e43c891455ed606c9585.png",
        "duration": 83,
        "price": 10,
        "vprice": 1,
        "views": 28,
        "favorites": 10,
        "shares": 0,
        "likes": 18,
        "is_like": 0,
        "url": "https://liketv.oss-cn-hongkong.aliyuncs.com/shendian/65.mp4"
      },
      {
        "track": "https://www.quicktv.vip/uploads/tracklist/20240911/fd107517806f1ac2564fef2fdd85d5af5.vtt",
        "id": 463533,
        "vid": 10858,
        "name": "66",
        "image": "https://liketv.oss-cn-hongkong.aliyuncs.com/btfolder2/uploads/20240111/9b137dcf3456e43c891455ed606c9585.png",
        "duration": 92,
        "price": 10,
        "vprice": 1,
        "views": 28,
        "favorites": 10,
        "shares": 0,
        "likes": 18,
        "is_like": 0,
        "url": "https://liketv.oss-cn-hongkong.aliyuncs.com/shendian/66.mp4"
      },
      {
        "track": "https://www.quicktv.vip/uploads/tracklist/20240911/f6d1b31eccce00385f9e45f7111667dcb.vtt",
        "id": 463534,
        "vid": 10858,
        "name": "67",
        "image": "https://liketv.oss-cn-hongkong.aliyuncs.com/btfolder2/uploads/20240111/9b137dcf3456e43c891455ed606c9585.png",
        "duration": 95,
        "price": 10,
        "vprice": 1,
        "views": 28,
        "favorites": 10,
        "shares": 0,
        "likes": 18,
        "is_like": 0,
        "url": "https://liketv.oss-cn-hongkong.aliyuncs.com/shendian/67.mp4"
      },
      {
        "track": "https://www.quicktv.vip/uploads/tracklist/20240911/fb1149350d9d146cd9a625a5d47d29b4e.vtt",
        "id": 463535,
        "vid": 10858,
        "name": "68",
        "image": "https://liketv.oss-cn-hongkong.aliyuncs.com/btfolder2/uploads/20240111/9b137dcf3456e43c891455ed606c9585.png",
        "duration": 94,
        "price": 10,
        "vprice": 1,
        "views": 28,
        "favorites": 10,
        "shares": 0,
        "likes": 18,
        "is_like": 0,
        "url": "https://liketv.oss-cn-hongkong.aliyuncs.com/shendian/68.mp4"
      },
      {
        "track": "https://www.quicktv.vip/uploads/tracklist/20240911/f34918b994a6a279cb8fbda49e27a6c55.vtt",
        "id": 463536,
        "vid": 10858,
        "name": "69",
        "image": "https://liketv.oss-cn-hongkong.aliyuncs.com/btfolder2/uploads/20240111/9b137dcf3456e43c891455ed606c9585.png",
        "duration": 90,
        "price": 10,
        "vprice": 1,
        "views": 28,
        "favorites": 10,
        "shares": 0,
        "likes": 18,
        "is_like": 0,
        "url": "https://liketv.oss-cn-hongkong.aliyuncs.com/shendian/69.mp4"
      },
      {
        "track": "https://www.quicktv.vip/uploads/tracklist/20240911/f39332bf9ee26a4ee980e4dbca6aaec56.vtt",
        "id": 463537,
        "vid": 10858,
        "name": "70",
        "image": "https://liketv.oss-cn-hongkong.aliyuncs.com/btfolder2/uploads/20240111/9b137dcf3456e43c891455ed606c9585.png",
        "duration": 93,
        "price": 10,
        "vprice": 1,
        "views": 28,
        "favorites": 10,
        "shares": 0,
        "likes": 18,
        "is_like": 0,
        "url": "https://liketv.oss-cn-hongkong.aliyuncs.com/shendian/70.mp4"
      },
      {
        "track": "https://www.quicktv.vip/uploads/tracklist/20240911/f2a0020d75c1dd1bf4310ac9b6b58d60c.vtt",
        "id": 463538,
        "vid": 10858,
        "name": "71",
        "image": "https://liketv.oss-cn-hongkong.aliyuncs.com/btfolder2/uploads/20240111/9b137dcf3456e43c891455ed606c9585.png",
        "duration": 93,
        "price": 10,
        "vprice": 1,
        "views": 28,
        "favorites": 10,
        "shares": 0,
        "likes": 18,
        "is_like": 0,
        "url": "https://liketv.oss-cn-hongkong.aliyuncs.com/shendian/71.mp4"
      },
      {
        "track": "https://www.quicktv.vip/uploads/tracklist/20240911/f94e0c5871aa68e36409077e4d7245b7a.vtt",
        "id": 463539,
        "vid": 10858,
        "name": "72",
        "image": "https://liketv.oss-cn-hongkong.aliyuncs.com/btfolder2/uploads/20240111/9b137dcf3456e43c891455ed606c9585.png",
        "duration": 93,
        "price": 10,
        "vprice": 1,
        "views": 28,
        "favorites": 10,
        "shares": 0,
        "likes": 18,
        "is_like": 0,
        "url": "https://liketv.oss-cn-hongkong.aliyuncs.com/shendian/72.mp4"
      },
      {
        "track": "https://www.quicktv.vip/uploads/tracklist/20240911/f6ebdeabaa10a5e4efe186bff0467900f.vtt",
        "id": 463540,
        "vid": 10858,
        "name": "73",
        "image": "https://liketv.oss-cn-hongkong.aliyuncs.com/btfolder2/uploads/20240111/9b137dcf3456e43c891455ed606c9585.png",
        "duration": 81,
        "price": 10,
        "vprice": 1,
        "views": 28,
        "favorites": 10,
        "shares": 0,
        "likes": 18,
        "is_like": 0,
        "url": "https://liketv.oss-cn-hongkong.aliyuncs.com/shendian/73.mp4"
      },
      {
        "track": "https://www.quicktv.vip/uploads/tracklist/20240911/fb74792a3efdb837096ef51056eb9c200.vtt",
        "id": 463541,
        "vid": 10858,
        "name": "74",
        "image": "https://liketv.oss-cn-hongkong.aliyuncs.com/btfolder2/uploads/20240111/9b137dcf3456e43c891455ed606c9585.png",
        "duration": 87,
        "price": 10,
        "vprice": 1,
        "views": 28,
        "favorites": 10,
        "shares": 0,
        "likes": 18,
        "is_like": 0,
        "url": "https://liketv.oss-cn-hongkong.aliyuncs.com/shendian/74.mp4"
      },
      {
        "track": "https://www.quicktv.vip/uploads/tracklist/20240911/f6c7bb9734d195cb1b7c37d5b3648a961.vtt",
        "id": 463542,
        "vid": 10858,
        "name": "75",
        "image": "https://liketv.oss-cn-hongkong.aliyuncs.com/btfolder2/uploads/20240111/9b137dcf3456e43c891455ed606c9585.png",
        "duration": 83,
        "price": 10,
        "vprice": 1,
        "views": 28,
        "favorites": 10,
        "shares": 0,
        "likes": 18,
        "is_like": 0,
        "url": "https://liketv.oss-cn-hongkong.aliyuncs.com/shendian/75.mp4"
      },
      {
        "track": "https://www.quicktv.vip/uploads/tracklist/20240911/fdb7f05cdadcf8676daa85848b663effd.vtt",
        "id": 463543,
        "vid": 10858,
        "name": "76",
        "image": "https://liketv.oss-cn-hongkong.aliyuncs.com/btfolder2/uploads/20240111/9b137dcf3456e43c891455ed606c9585.png",
        "duration": 88,
        "price": 10,
        "vprice": 1,
        "views": 28,
        "favorites": 10,
        "shares": 0,
        "likes": 18,
        "is_like": 0,
        "url": "https://liketv.oss-cn-hongkong.aliyuncs.com/shendian/76.mp4"
      },
      {
        "track": "https://www.quicktv.vip/uploads/tracklist/20240911/f5b8b76e8c7185380ced5ab55ac4564d9.vtt",
        "id": 463544,
        "vid": 10858,
        "name": "77",
        "image": "https://liketv.oss-cn-hongkong.aliyuncs.com/btfolder2/uploads/20240111/9b137dcf3456e43c891455ed606c9585.png",
        "duration": 84,
        "price": 10,
        "vprice": 1,
        "views": 28,
        "favorites": 10,
        "shares": 0,
        "likes": 18,
        "is_like": 0,
        "url": "https://liketv.oss-cn-hongkong.aliyuncs.com/shendian/77.mp4"
      },
      {
        "track": "https://www.quicktv.vip/uploads/tracklist/20240911/fa526078b33aebc3ed7be7d75ce1f131d.vtt",
        "id": 463545,
        "vid": 10858,
        "name": "78",
        "image": "https://liketv.oss-cn-hongkong.aliyuncs.com/btfolder2/uploads/20240111/9b137dcf3456e43c891455ed606c9585.png",
        "duration": 90,
        "price": 10,
        "vprice": 1,
        "views": 28,
        "favorites": 10,
        "shares": 0,
        "likes": 18,
        "is_like": 0,
        "url": "https://liketv.oss-cn-hongkong.aliyuncs.com/shendian/78.mp4"
      },
      {
        "track": "https://www.quicktv.vip/uploads/tracklist/20240911/fd949182960b1d70dffe3c30b5b57660a.vtt",
        "id": 463546,
        "vid": 10858,
        "name": "79",
        "image": "https://liketv.oss-cn-hongkong.aliyuncs.com/btfolder2/uploads/20240111/9b137dcf3456e43c891455ed606c9585.png",
        "duration": 89,
        "price": 10,
        "vprice": 1,
        "views": 28,
        "favorites": 10,
        "shares": 0,
        "likes": 18,
        "is_like": 0,
        "url": "https://liketv.oss-cn-hongkong.aliyuncs.com/shendian/79.mp4"
      },
      {
        "track": "https://www.quicktv.vip/uploads/tracklist/20240911/f11afd1be2994bd2414b81119c785cfbb.vtt",
        "id": 463547,
        "vid": 10858,
        "name": "80",
        "image": "https://liketv.oss-cn-hongkong.aliyuncs.com/btfolder2/uploads/20240111/9b137dcf3456e43c891455ed606c9585.png",
        "duration": 89,
        "price": 10,
        "vprice": 1,
        "views": 28,
        "favorites": 10,
        "shares": 0,
        "likes": 18,
        "is_like": 0,
        "url": "https://liketv.oss-cn-hongkong.aliyuncs.com/shendian/80.mp4"
      }
    ],
    "adsurl": "https://liketv.oss-cn-hongkong.aliyuncs.com/00quicktv/28.mp4",
    "tags_arr": [],
    "category_text_arr": [],
    "year_text": "",
    "area_text": ""
  }
}